<PnPUnitTestResults>
  <PnPTestSummary>
    <PnPConfigurationToTest>OnlineAppOnly</PnPConfigurationToTest>
    <TestDate>Tuesday, April 19, 2016</TestDate>
    <TestTime>10:39 PM</TestTime>
    <PnPBranch>dev</PnPBranch>
    <VSBuildConfiguration>debug</VSBuildConfiguration>
    <NumberOfTests>305</NumberOfTests>
    <ElapsedTime>0h 44m 14s</ElapsedTime>
    <FailedTests>2</FailedTests>
    <SkippedTests>39</SkippedTests>
    <PassedTests>264</PassedTests>
    <MDResultFile>c:\pnpbuildtemp\PnPUnitTestResults-20160419-OnlineAppOnly-635966231840940373.md</MDResultFile>
  </PnPTestSummary>
  <PnPTestSummary>
    <PnPConfigurationToTest>OnlineCred</PnPConfigurationToTest>
    <TestDate>Monday, April 18, 2016</TestDate>
    <TestTime>9:48 PM</TestTime>
    <PnPBranch>dev</PnPBranch>
    <VSBuildConfiguration>debug</VSBuildConfiguration>
    <NumberOfTests>305</NumberOfTests>
    <ElapsedTime>0h 51m 17s</ElapsedTime>
    <FailedTests>0</FailedTests>
    <SkippedTests>7</SkippedTests>
    <PassedTests>298</PassedTests>
    <MDResultFile>c:\pnpbuildtemp\PnPUnitTestResults-20160418-OnlineCred-635966200882486534.md</MDResultFile>
  </PnPTestSummary>
  <PnPTestSummary>
    <PnPConfigurationToTest>OnPremAppOnly</PnPConfigurationToTest>
    <TestDate>Monday, April 18, 2016</TestDate>
    <TestTime>9:25 PM</TestTime>
    <PnPBranch>dev</PnPBranch>
    <VSBuildConfiguration>debug15</VSBuildConfiguration>
    <NumberOfTests>297</NumberOfTests>
    <ElapsedTime>0h 22m 39s</ElapsedTime>
    <FailedTests>3</FailedTests>
    <SkippedTests>51</SkippedTests>
    <PassedTests>243</PassedTests>
    <MDResultFile>c:\pnpbuildtemp\PnPUnitTestResults-20160418-OnPremAppOnly-635966187104834098.md</MDResultFile>
  </PnPTestSummary>
  <PnPTestSummary>
    <PnPConfigurationToTest>OnPremCred</PnPConfigurationToTest>
    <TestDate>Monday, April 18, 2016</TestDate>
    <TestTime>9:00 PM</TestTime>
    <PnPBranch>dev</PnPBranch>
    <VSBuildConfiguration>debug15</VSBuildConfiguration>
    <NumberOfTests>297</NumberOfTests>
    <ElapsedTime>0h 24m 30s</ElapsedTime>
    <FailedTests>3</FailedTests>
    <SkippedTests>21</SkippedTests>
    <PassedTests>273</PassedTests>
    <MDResultFile>c:\pnpbuildtemp\PnPUnitTestResults-20160418-OnPremCred-635966172214642178.md</MDResultFile>
  </PnPTestSummary>
  <PnPTestSummary>
    <PnPConfigurationToTest>OnlineAppOnly</PnPConfigurationToTest>
    <TestDate>Monday, April 18, 2016</TestDate>
    <TestTime>10:37 PM</TestTime>
    <PnPBranch>dev</PnPBranch>
    <VSBuildConfiguration>debug</VSBuildConfiguration>
    <NumberOfTests>305</NumberOfTests>
    <ElapsedTime>0h 42m 56s</ElapsedTime>
    <FailedTests>3</FailedTests>
    <SkippedTests>39</SkippedTests>
    <PassedTests>263</PassedTests>
    <MDResultFile>c:\pnpbuildtemp\PnPUnitTestResults-20160418-OnlineAppOnly-635965366225987516.md</MDResultFile>
  </PnPTestSummary>
  <PnPTestSummary>
    <PnPConfigurationToTest>OnlineCred</PnPConfigurationToTest>
    <TestDate>Sunday, April 17, 2016</TestDate>
    <TestTime>9:48 PM</TestTime>
    <PnPBranch>dev</PnPBranch>
    <VSBuildConfiguration>debug</VSBuildConfiguration>
    <NumberOfTests>305</NumberOfTests>
    <ElapsedTime>0h 48m 0s</ElapsedTime>
    <FailedTests>3</FailedTests>
    <SkippedTests>7</SkippedTests>
    <PassedTests>295</PassedTests>
    <MDResultFile>c:\pnpbuildtemp\PnPUnitTestResults-20160417-OnlineCred-635965337233085769.md</MDResultFile>
  </PnPTestSummary>
  <PnPTestSummary>
    <PnPConfigurationToTest>OnPremAppOnly</PnPConfigurationToTest>
    <TestDate>Sunday, April 17, 2016</TestDate>
    <TestTime>9:25 PM</TestTime>
    <PnPBranch>dev</PnPBranch>
    <VSBuildConfiguration>debug15</VSBuildConfiguration>
    <NumberOfTests>297</NumberOfTests>
    <ElapsedTime>0h 22m 58s</ElapsedTime>
    <FailedTests>3</FailedTests>
    <SkippedTests>51</SkippedTests>
    <PassedTests>243</PassedTests>
    <MDResultFile>c:\pnpbuildtemp\PnPUnitTestResults-20160417-OnPremAppOnly-635965323252580684.md</MDResultFile>
  </PnPTestSummary>
  <PnPTestSummary>
    <PnPConfigurationToTest>OnPremCred</PnPConfigurationToTest>
    <TestDate>Sunday, April 17, 2016</TestDate>
    <TestTime>9:00 PM</TestTime>
    <PnPBranch>dev</PnPBranch>
    <VSBuildConfiguration>debug15</VSBuildConfiguration>
    <NumberOfTests>297</NumberOfTests>
    <ElapsedTime>0h 24m 35s</ElapsedTime>
    <FailedTests>3</FailedTests>
    <SkippedTests>21</SkippedTests>
    <PassedTests>273</PassedTests>
    <MDResultFile>c:\pnpbuildtemp\PnPUnitTestResults-20160417-OnPremCred-635965308321365733.md</MDResultFile>
  </PnPTestSummary>
  <PnPTestSummary>
    <PnPConfigurationToTest>OnlineAppOnly</PnPConfigurationToTest>
    <TestDate>Sunday, April 17, 2016</TestDate>
    <TestTime>10:47 PM</TestTime>
    <PnPBranch>dev</PnPBranch>
    <VSBuildConfiguration>debug</VSBuildConfiguration>
    <NumberOfTests>305</NumberOfTests>
    <ElapsedTime>0h 47m 12s</ElapsedTime>
    <FailedTests>3</FailedTests>
    <SkippedTests>39</SkippedTests>
    <PassedTests>263</PassedTests>
    <MDResultFile>c:\pnpbuildtemp\PnPUnitTestResults-20160417-OnlineAppOnly-635964508545253365.md</MDResultFile>
  </PnPTestSummary>
  <PnPTestSummary>
    <PnPConfigurationToTest>OnlineCred</PnPConfigurationToTest>
    <TestDate>Saturday, April 16, 2016</TestDate>
    <TestTime>9:53 PM</TestTime>
    <PnPBranch>dev</PnPBranch>
    <VSBuildConfiguration>debug</VSBuildConfiguration>
    <NumberOfTests>305</NumberOfTests>
    <ElapsedTime>0h 53m 42s</ElapsedTime>
    <FailedTests>2</FailedTests>
    <SkippedTests>7</SkippedTests>
    <PassedTests>296</PassedTests>
    <MDResultFile>c:\pnpbuildtemp\PnPUnitTestResults-20160416-OnlineCred-635964476075510596.md</MDResultFile>
  </PnPTestSummary>
  <PnPTestSummary>
    <PnPConfigurationToTest>OnPremAppOnly</PnPConfigurationToTest>
    <TestDate>Saturday, April 16, 2016</TestDate>
    <TestTime>9:25 PM</TestTime>
    <PnPBranch>dev</PnPBranch>
    <VSBuildConfiguration>debug15</VSBuildConfiguration>
    <NumberOfTests>297</NumberOfTests>
    <ElapsedTime>0h 27m 39s</ElapsedTime>
    <FailedTests>3</FailedTests>
    <SkippedTests>51</SkippedTests>
    <PassedTests>243</PassedTests>
    <MDResultFile>c:\pnpbuildtemp\PnPUnitTestResults-20160416-OnPremAppOnly-635964459214578897.md</MDResultFile>
  </PnPTestSummary>
  <PnPTestSummary>
    <PnPConfigurationToTest>OnPremCred</PnPConfigurationToTest>
    <TestDate>Saturday, April 16, 2016</TestDate>
    <TestTime>9:00 PM</TestTime>
    <PnPBranch>dev</PnPBranch>
    <VSBuildConfiguration>debug15</VSBuildConfiguration>
    <NumberOfTests>297</NumberOfTests>
    <ElapsedTime>0h 24m 43s</ElapsedTime>
    <FailedTests>3</FailedTests>
    <SkippedTests>21</SkippedTests>
    <PassedTests>273</PassedTests>
    <MDResultFile>c:\pnpbuildtemp\PnPUnitTestResults-20160416-OnPremCred-635964444198448494.md</MDResultFile>
  </PnPTestSummary>
  <PnPTestSummary>
    <PnPConfigurationToTest>OnlineAppOnly</PnPConfigurationToTest>
    <TestDate>Friday, April 15, 2016</TestDate>
    <TestTime>9:47 PM</TestTime>
    <PnPBranch>dev</PnPBranch>
    <VSBuildConfiguration>debug</VSBuildConfiguration>
    <NumberOfTests>305</NumberOfTests>
    <ElapsedTime>0h 50m 53s</ElapsedTime>
    <FailedTests>2</FailedTests>
    <SkippedTests>39</SkippedTests>
    <PassedTests>264</PassedTests>
    <MDResultFile>c:\pnpbuildtemp\PnPUnitTestResults-20160415-OnlineAppOnly-635963608332897792.md</MDResultFile>
  </PnPTestSummary>
  <PnPTestSummary>
    <PnPConfigurationToTest>OnPremAppOnly</PnPConfigurationToTest>
    <TestDate>Friday, April 15, 2016</TestDate>
    <TestTime>9:24 PM</TestTime>
    <PnPBranch>dev</PnPBranch>
    <VSBuildConfiguration>debug15</VSBuildConfiguration>
    <NumberOfTests>297</NumberOfTests>
    <ElapsedTime>0h 22m 7s</ElapsedTime>
    <FailedTests>3</FailedTests>
    <SkippedTests>51</SkippedTests>
    <PassedTests>243</PassedTests>
    <MDResultFile>c:\pnpbuildtemp\PnPUnitTestResults-20160415-OnPremAppOnly-635963594804564180.md</MDResultFile>
  </PnPTestSummary>
  <PnPTestSummary>
    <PnPConfigurationToTest>OnPremCred</PnPConfigurationToTest>
    <TestDate>Friday, April 15, 2016</TestDate>
    <TestTime>9:00 PM</TestTime>
    <PnPBranch>dev</PnPBranch>
    <VSBuildConfiguration>debug15</VSBuildConfiguration>
    <NumberOfTests>297</NumberOfTests>
    <ElapsedTime>0h 24m 1s</ElapsedTime>
    <FailedTests>3</FailedTests>
    <SkippedTests>21</SkippedTests>
    <PassedTests>273</PassedTests>
    <MDResultFile>c:\pnpbuildtemp\PnPUnitTestResults-20160415-OnPremCred-635963580208152490.md</MDResultFile>
  </PnPTestSummary>
  <PnPTestSummary>
    <PnPConfigurationToTest>OnlineAppOnly</PnPConfigurationToTest>
    <TestDate>Friday, April 15, 2016</TestDate>
    <TestTime>10:33 PM</TestTime>
    <PnPBranch>dev</PnPBranch>
    <VSBuildConfiguration>debug</VSBuildConfiguration>
    <NumberOfTests>303</NumberOfTests>
    <ElapsedTime>0h 46m 5s</ElapsedTime>
    <FailedTests>5</FailedTests>
    <SkippedTests>39</SkippedTests>
    <PassedTests>259</PassedTests>
    <MDResultFile>c:\pnpbuildtemp\PnPUnitTestResults-20160415-OnlineAppOnly-635962772184183412.md</MDResultFile>
  </PnPTestSummary>
  <PnPTestSummary>
    <PnPConfigurationToTest>OnlineCred</PnPConfigurationToTest>
    <TestDate>Thursday, April 14, 2016</TestDate>
    <TestTime>9:47 PM</TestTime>
    <PnPBranch>dev</PnPBranch>
    <VSBuildConfiguration>debug</VSBuildConfiguration>
    <NumberOfTests>303</NumberOfTests>
    <ElapsedTime>0h 45m 52s</ElapsedTime>
    <FailedTests>4</FailedTests>
    <SkippedTests>7</SkippedTests>
    <PassedTests>292</PassedTests>
    <MDResultFile>c:\pnpbuildtemp\PnPUnitTestResults-20160414-OnlineCred-635962744483045786.md</MDResultFile>
  </PnPTestSummary>
  <PnPTestSummary>
    <PnPConfigurationToTest>OnPremAppOnly</PnPConfigurationToTest>
    <TestDate>Thursday, April 14, 2016</TestDate>
    <TestTime>9:25 PM</TestTime>
    <PnPBranch>dev</PnPBranch>
    <VSBuildConfiguration>debug15</VSBuildConfiguration>
    <NumberOfTests>295</NumberOfTests>
    <ElapsedTime>0h 21m 59s</ElapsedTime>
    <FailedTests>3</FailedTests>
    <SkippedTests>51</SkippedTests>
    <PassedTests>241</PassedTests>
    <MDResultFile>c:\pnpbuildtemp\PnPUnitTestResults-20160414-OnPremAppOnly-635962731104894511.md</MDResultFile>
  </PnPTestSummary>
  <PnPTestSummary>
    <PnPConfigurationToTest>OnPremCred</PnPConfigurationToTest>
    <TestDate>Thursday, April 14, 2016</TestDate>
    <TestTime>9:00 PM</TestTime>
    <PnPBranch>dev</PnPBranch>
    <VSBuildConfiguration>debug15</VSBuildConfiguration>
    <NumberOfTests>295</NumberOfTests>
    <ElapsedTime>0h 24m 31s</ElapsedTime>
    <FailedTests>3</FailedTests>
    <SkippedTests>21</SkippedTests>
    <PassedTests>271</PassedTests>
    <MDResultFile>c:\pnpbuildtemp\PnPUnitTestResults-20160414-OnPremCred-635962716208671984.md</MDResultFile>
  </PnPTestSummary>
  <PnPTestSummary>
    <PnPConfigurationToTest>OnlineAppOnly</PnPConfigurationToTest>
    <TestDate>Thursday, April 14, 2016</TestDate>
    <TestTime>10:42 PM</TestTime>
    <PnPBranch>dev</PnPBranch>
    <VSBuildConfiguration>debug</VSBuildConfiguration>
    <NumberOfTests>303</NumberOfTests>
    <ElapsedTime>0h 51m 32s</ElapsedTime>
    <FailedTests>2</FailedTests>
    <SkippedTests>39</SkippedTests>
    <PassedTests>262</PassedTests>
    <MDResultFile>c:\pnpbuildtemp\PnPUnitTestResults-20160414-OnlineAppOnly-635961913604842839.md</MDResultFile>
  </PnPTestSummary>
  <PnPTestSummary>
    <PnPConfigurationToTest>OnlineCred</PnPConfigurationToTest>
    <TestDate>Wednesday, April 13, 2016</TestDate>
    <TestTime>9:46 PM</TestTime>
    <PnPBranch>dev</PnPBranch>
    <VSBuildConfiguration>debug</VSBuildConfiguration>
    <NumberOfTests>303</NumberOfTests>
    <ElapsedTime>0h 55m 31s</ElapsedTime>
    <FailedTests>2</FailedTests>
    <SkippedTests>7</SkippedTests>
    <PassedTests>294</PassedTests>
    <MDResultFile>c:\pnpbuildtemp\PnPUnitTestResults-20160413-OnlineCred-635961880107255255.md</MDResultFile>
  </PnPTestSummary>
  <PnPTestSummary>
    <PnPConfigurationToTest>OnPremAppOnly</PnPConfigurationToTest>
    <TestDate>Wednesday, April 13, 2016</TestDate>
    <TestTime>9:24 PM</TestTime>
    <PnPBranch>dev</PnPBranch>
    <VSBuildConfiguration>debug15</VSBuildConfiguration>
    <NumberOfTests>295</NumberOfTests>
    <ElapsedTime>0h 22m 4s</ElapsedTime>
    <FailedTests>3</FailedTests>
    <SkippedTests>51</SkippedTests>
    <PassedTests>241</PassedTests>
    <MDResultFile>c:\pnpbuildtemp\PnPUnitTestResults-20160413-OnPremAppOnly-635961866676320667.md</MDResultFile>
  </PnPTestSummary>
  <PnPTestSummary>
    <PnPConfigurationToTest>OnPremCred</PnPConfigurationToTest>
    <TestDate>Wednesday, April 13, 2016</TestDate>
    <TestTime>9:00 PM</TestTime>
    <PnPBranch>dev</PnPBranch>
    <VSBuildConfiguration>debug15</VSBuildConfiguration>
    <NumberOfTests>295</NumberOfTests>
    <ElapsedTime>0h 23m 49s</ElapsedTime>
    <FailedTests>3</FailedTests>
    <SkippedTests>21</SkippedTests>
    <PassedTests>271</PassedTests>
    <MDResultFile>c:\pnpbuildtemp\PnPUnitTestResults-20160413-OnPremCred-635961852201935732.md</MDResultFile>
  </PnPTestSummary>
  <PnPTestSummary>
    <PnPConfigurationToTest>OnlineAppOnly</PnPConfigurationToTest>
    <TestDate>Tuesday, April 12, 2016</TestDate>
    <TestTime>10:46 PM</TestTime>
    <PnPBranch>dev</PnPBranch>
    <VSBuildConfiguration>debug</VSBuildConfiguration>
    <NumberOfTests>303</NumberOfTests>
    <ElapsedTime>0h 45m 36s</ElapsedTime>
    <FailedTests>2</FailedTests>
    <SkippedTests>39</SkippedTests>
    <PassedTests>262</PassedTests>
    <MDResultFile>c:\pnpbuildtemp\PnPUnitTestResults-20160412-OnlineAppOnly-635960188028397607.md</MDResultFile>
  </PnPTestSummary>
  <PnPTestSummary>
    <PnPConfigurationToTest>OnlineCred</PnPConfigurationToTest>
    <TestDate>Monday, April 11, 2016</TestDate>
    <TestTime>9:47 PM</TestTime>
    <PnPBranch>dev</PnPBranch>
    <VSBuildConfiguration>debug</VSBuildConfiguration>
    <NumberOfTests>303</NumberOfTests>
    <ElapsedTime>0h 58m 19s</ElapsedTime>
    <FailedTests>2</FailedTests>
    <SkippedTests>7</SkippedTests>
    <PassedTests>294</PassedTests>
    <MDResultFile>c:\pnpbuildtemp\PnPUnitTestResults-20160411-OnlineCred-635960152686268296.md</MDResultFile>
  </PnPTestSummary>
  <PnPTestSummary>
    <PnPConfigurationToTest>OnPremAppOnly</PnPConfigurationToTest>
    <TestDate>Monday, April 11, 2016</TestDate>
    <TestTime>9:25 PM</TestTime>
    <PnPBranch>dev</PnPBranch>
    <VSBuildConfiguration>debug15</VSBuildConfiguration>
    <NumberOfTests>295</NumberOfTests>
    <ElapsedTime>0h 21m 40s</ElapsedTime>
    <FailedTests>3</FailedTests>
    <SkippedTests>51</SkippedTests>
    <PassedTests>241</PassedTests>
    <MDResultFile>c:\pnpbuildtemp\PnPUnitTestResults-20160411-OnPremAppOnly-635960139328780687.md</MDResultFile>
  </PnPTestSummary>
  <PnPTestSummary>
    <PnPConfigurationToTest>OnPremCred</PnPConfigurationToTest>
    <TestDate>Monday, April 11, 2016</TestDate>
    <TestTime>9:01 PM</TestTime>
    <PnPBranch>dev</PnPBranch>
    <VSBuildConfiguration>debug15</VSBuildConfiguration>
    <NumberOfTests>295</NumberOfTests>
    <ElapsedTime>0h 23m 54s</ElapsedTime>
    <FailedTests>3</FailedTests>
    <SkippedTests>21</SkippedTests>
    <PassedTests>271</PassedTests>
    <MDResultFile>c:\pnpbuildtemp\PnPUnitTestResults-20160411-OnPremCred-635960124647753674.md</MDResultFile>
  </PnPTestSummary>
  <PnPTestSummary>
    <PnPConfigurationToTest>OnlineAppOnly</PnPConfigurationToTest>
    <TestDate>Monday, April 11, 2016</TestDate>
    <TestTime>10:37 PM</TestTime>
    <PnPBranch>dev</PnPBranch>
    <VSBuildConfiguration>debug</VSBuildConfiguration>
    <NumberOfTests>303</NumberOfTests>
    <ElapsedTime>0h 46m 56s</ElapsedTime>
    <FailedTests>2</FailedTests>
    <SkippedTests>39</SkippedTests>
    <PassedTests>262</PassedTests>
    <MDResultFile>c:\pnpbuildtemp\PnPUnitTestResults-20160411-OnlineAppOnly-635959318634988045.md</MDResultFile>
  </PnPTestSummary>
  <PnPTestSummary>
    <PnPConfigurationToTest>OnlineCred</PnPConfigurationToTest>
    <TestDate>Sunday, April 10, 2016</TestDate>
    <TestTime>9:47 PM</TestTime>
    <PnPBranch>dev</PnPBranch>
    <VSBuildConfiguration>debug</VSBuildConfiguration>
    <NumberOfTests>303</NumberOfTests>
    <ElapsedTime>0h 50m 2s</ElapsedTime>
    <FailedTests>2</FailedTests>
    <SkippedTests>7</SkippedTests>
    <PassedTests>294</PassedTests>
    <MDResultFile>c:\pnpbuildtemp\PnPUnitTestResults-20160410-OnlineCred-635959288360845573.md</MDResultFile>
  </PnPTestSummary>
  <PnPTestSummary>
    <PnPConfigurationToTest>OnPremAppOnly</PnPConfigurationToTest>
    <TestDate>Sunday, April 10, 2016</TestDate>
    <TestTime>9:25 PM</TestTime>
    <PnPBranch>dev</PnPBranch>
    <VSBuildConfiguration>debug15</VSBuildConfiguration>
    <NumberOfTests>295</NumberOfTests>
    <ElapsedTime>0h 21m 18s</ElapsedTime>
    <FailedTests>3</FailedTests>
    <SkippedTests>51</SkippedTests>
    <PassedTests>241</PassedTests>
    <MDResultFile>c:\pnpbuildtemp\PnPUnitTestResults-20160410-OnPremAppOnly-635959275157060033.md</MDResultFile>
  </PnPTestSummary>
  <PnPTestSummary>
    <PnPConfigurationToTest>OnPremCred</PnPConfigurationToTest>
    <TestDate>Sunday, April 10, 2016</TestDate>
    <TestTime>9:00 PM</TestTime>
    <PnPBranch>dev</PnPBranch>
    <VSBuildConfiguration>debug15</VSBuildConfiguration>
    <NumberOfTests>295</NumberOfTests>
    <ElapsedTime>0h 24m 0s</ElapsedTime>
    <FailedTests>3</FailedTests>
    <SkippedTests>21</SkippedTests>
    <PassedTests>271</PassedTests>
    <MDResultFile>c:\pnpbuildtemp\PnPUnitTestResults-20160410-OnPremCred-635959260497856419.md</MDResultFile>
  </PnPTestSummary>
  <PnPTestSummary>
    <PnPConfigurationToTest>OnlineAppOnly</PnPConfigurationToTest>
    <TestDate>Sunday, April 10, 2016</TestDate>
    <TestTime>10:43 PM</TestTime>
    <PnPBranch>dev</PnPBranch>
    <VSBuildConfiguration>debug</VSBuildConfiguration>
    <NumberOfTests>303</NumberOfTests>
    <ElapsedTime>0h 46m 53s</ElapsedTime>
    <FailedTests>4</FailedTests>
    <SkippedTests>39</SkippedTests>
    <PassedTests>260</PassedTests>
    <MDResultFile>c:\pnpbuildtemp\PnPUnitTestResults-20160410-OnlineAppOnly-635958458159281016.md</MDResultFile>
  </PnPTestSummary>
  <PnPTestSummary>
    <PnPConfigurationToTest>OnlineCred</PnPConfigurationToTest>
    <TestDate>Saturday, April 9, 2016</TestDate>
    <TestTime>9:53 PM</TestTime>
    <PnPBranch>dev</PnPBranch>
    <VSBuildConfiguration>debug</VSBuildConfiguration>
    <NumberOfTests>303</NumberOfTests>
    <ElapsedTime>0h 49m 16s</ElapsedTime>
    <FailedTests>2</FailedTests>
    <SkippedTests>7</SkippedTests>
    <PassedTests>294</PassedTests>
    <MDResultFile>c:\pnpbuildtemp\PnPUnitTestResults-20160409-OnlineCred-635958427994760945.md</MDResultFile>
  </PnPTestSummary>
  <PnPTestSummary>
    <PnPConfigurationToTest>OnPremAppOnly</PnPConfigurationToTest>
    <TestDate>Saturday, April 9, 2016</TestDate>
    <TestTime>9:25 PM</TestTime>
    <PnPBranch>dev</PnPBranch>
    <VSBuildConfiguration>debug15</VSBuildConfiguration>
    <NumberOfTests>295</NumberOfTests>
    <ElapsedTime>0h 26m 38s</ElapsedTime>
    <FailedTests>3</FailedTests>
    <SkippedTests>51</SkippedTests>
    <PassedTests>241</PassedTests>
    <MDResultFile>c:\pnpbuildtemp\PnPUnitTestResults-20160409-OnPremAppOnly-635958411409490008.md</MDResultFile>
  </PnPTestSummary>
  <PnPTestSummary>
    <PnPConfigurationToTest>OnPremCred</PnPConfigurationToTest>
    <TestDate>Saturday, April 9, 2016</TestDate>
    <TestTime>9:00 PM</TestTime>
    <PnPBranch>dev</PnPBranch>
    <VSBuildConfiguration>debug15</VSBuildConfiguration>
    <NumberOfTests>295</NumberOfTests>
    <ElapsedTime>0h 24m 19s</ElapsedTime>
    <FailedTests>3</FailedTests>
    <SkippedTests>21</SkippedTests>
    <PassedTests>271</PassedTests>
    <MDResultFile>c:\pnpbuildtemp\PnPUnitTestResults-20160409-OnPremCred-635958396566299412.md</MDResultFile>
  </PnPTestSummary>
  <PnPTestSummary>
    <PnPConfigurationToTest>OnlineAppOnly</PnPConfigurationToTest>
    <TestDate>Saturday, April 9, 2016</TestDate>
    <TestTime>10:44 PM</TestTime>
    <PnPBranch>dev</PnPBranch>
    <VSBuildConfiguration>debug</VSBuildConfiguration>
    <NumberOfTests>303</NumberOfTests>
    <ElapsedTime>0h 53m 27s</ElapsedTime>
    <FailedTests>3</FailedTests>
    <SkippedTests>39</SkippedTests>
    <PassedTests>261</PassedTests>
    <MDResultFile>c:\pnpbuildtemp\PnPUnitTestResults-20160409-OnlineAppOnly-635957594515375881.md</MDResultFile>
  </PnPTestSummary>
  <PnPTestSummary>
    <PnPConfigurationToTest>OnlineCred</PnPConfigurationToTest>
    <TestDate>Friday, April 8, 2016</TestDate>
    <TestTime>9:48 PM</TestTime>
    <PnPBranch>dev</PnPBranch>
    <VSBuildConfiguration>debug</VSBuildConfiguration>
    <NumberOfTests>303</NumberOfTests>
    <ElapsedTime>0h 55m 42s</ElapsedTime>
    <FailedTests>4</FailedTests>
    <SkippedTests>7</SkippedTests>
    <PassedTests>292</PassedTests>
    <MDResultFile>c:\pnpbuildtemp\PnPUnitTestResults-20160408-OnlineCred-635957560830981274.md</MDResultFile>
  </PnPTestSummary>
  <PnPTestSummary>
    <PnPConfigurationToTest>OnPremAppOnly</PnPConfigurationToTest>
    <TestDate>Friday, April 8, 2016</TestDate>
    <TestTime>9:25 PM</TestTime>
    <PnPBranch>dev</PnPBranch>
    <VSBuildConfiguration>debug15</VSBuildConfiguration>
    <NumberOfTests>295</NumberOfTests>
    <ElapsedTime>0h 22m 14s</ElapsedTime>
    <FailedTests>3</FailedTests>
    <SkippedTests>51</SkippedTests>
    <PassedTests>241</PassedTests>
    <MDResultFile>c:\pnpbuildtemp\PnPUnitTestResults-20160408-OnPremAppOnly-635957547026149402.md</MDResultFile>
  </PnPTestSummary>
  <PnPTestSummary>
    <PnPConfigurationToTest>OnPremCred</PnPConfigurationToTest>
    <TestDate>Friday, April 8, 2016</TestDate>
    <TestTime>9:00 PM</TestTime>
    <PnPBranch>dev</PnPBranch>
    <VSBuildConfiguration>debug15</VSBuildConfiguration>
    <NumberOfTests>295</NumberOfTests>
    <ElapsedTime>0h 23m 47s</ElapsedTime>
    <FailedTests>3</FailedTests>
    <SkippedTests>21</SkippedTests>
    <PassedTests>271</PassedTests>
    <MDResultFile>c:\pnpbuildtemp\PnPUnitTestResults-20160408-OnPremCred-635957532491212997.md</MDResultFile>
  </PnPTestSummary>
  <PnPTestSummary>
    <PnPConfigurationToTest>OnlineAppOnly</PnPConfigurationToTest>
    <TestDate>Friday, April 8, 2016</TestDate>
    <TestTime>10:40 PM</TestTime>
    <PnPBranch>dev</PnPBranch>
    <VSBuildConfiguration>debug</VSBuildConfiguration>
    <NumberOfTests>303</NumberOfTests>
    <ElapsedTime>0h 43m 22s</ElapsedTime>
    <FailedTests>4</FailedTests>
    <SkippedTests>39</SkippedTests>
    <PassedTests>260</PassedTests>
    <MDResultFile>c:\pnpbuildtemp\PnPUnitTestResults-20160408-OnlineAppOnly-635956728348664928.md</MDResultFile>
  </PnPTestSummary>
  <PnPTestSummary>
    <PnPConfigurationToTest>OnlineCred</PnPConfigurationToTest>
    <TestDate>Thursday, April 7, 2016</TestDate>
    <TestTime>9:48 PM</TestTime>
    <PnPBranch>dev</PnPBranch>
    <VSBuildConfiguration>debug</VSBuildConfiguration>
    <NumberOfTests>303</NumberOfTests>
    <ElapsedTime>0h 52m 3s</ElapsedTime>
    <FailedTests>2</FailedTests>
    <SkippedTests>7</SkippedTests>
    <PassedTests>294</PassedTests>
    <MDResultFile>c:\pnpbuildtemp\PnPUnitTestResults-20160407-OnlineCred-635956696863377903.md</MDResultFile>
  </PnPTestSummary>
  <PnPTestSummary>
    <PnPConfigurationToTest>OnPremAppOnly</PnPConfigurationToTest>
    <TestDate>Thursday, April 7, 2016</TestDate>
    <TestTime>9:25 PM</TestTime>
    <PnPBranch>dev</PnPBranch>
    <VSBuildConfiguration>debug15</VSBuildConfiguration>
    <NumberOfTests>295</NumberOfTests>
    <ElapsedTime>0h 22m 13s</ElapsedTime>
    <FailedTests>3</FailedTests>
    <SkippedTests>51</SkippedTests>
    <PassedTests>241</PassedTests>
    <MDResultFile>c:\pnpbuildtemp\PnPUnitTestResults-20160407-OnPremAppOnly-635956683041016568.md</MDResultFile>
  </PnPTestSummary>
  <PnPTestSummary>
    <PnPConfigurationToTest>OnPremCred</PnPConfigurationToTest>
    <TestDate>Thursday, April 7, 2016</TestDate>
    <TestTime>9:00 PM</TestTime>
    <PnPBranch>dev</PnPBranch>
    <VSBuildConfiguration>debug15</VSBuildConfiguration>
    <NumberOfTests>295</NumberOfTests>
    <ElapsedTime>0h 23m 52s</ElapsedTime>
    <FailedTests>3</FailedTests>
    <SkippedTests>21</SkippedTests>
    <PassedTests>271</PassedTests>
    <MDResultFile>c:\pnpbuildtemp\PnPUnitTestResults-20160407-OnPremCred-635956668463991301.md</MDResultFile>
  </PnPTestSummary>
  <PnPTestSummary>
    <PnPConfigurationToTest>OnlineAppOnly</PnPConfigurationToTest>
    <TestDate>Thursday, April 7, 2016</TestDate>
    <TestTime>10:48 PM</TestTime>
    <PnPBranch>dev</PnPBranch>
    <VSBuildConfiguration>debug</VSBuildConfiguration>
    <NumberOfTests>303</NumberOfTests>
    <ElapsedTime>0h 42m 11s</ElapsedTime>
    <FailedTests>4</FailedTests>
    <SkippedTests>39</SkippedTests>
    <PassedTests>260</PassedTests>
    <MDResultFile>c:\pnpbuildtemp\PnPUnitTestResults-20160407-OnlineAppOnly-635955869056692332.md</MDResultFile>
  </PnPTestSummary>
  <PnPTestSummary>
    <PnPConfigurationToTest>OnlineCred</PnPConfigurationToTest>
    <TestDate>Wednesday, April 6, 2016</TestDate>
    <TestTime>9:48 PM</TestTime>
    <PnPBranch>dev</PnPBranch>
    <VSBuildConfiguration>debug</VSBuildConfiguration>
    <NumberOfTests>303</NumberOfTests>
    <ElapsedTime>0h 59m 57s</ElapsedTime>
    <FailedTests>2</FailedTests>
    <SkippedTests>7</SkippedTests>
    <PassedTests>294</PassedTests>
    <MDResultFile>c:\pnpbuildtemp\PnPUnitTestResults-20160406-OnlineCred-635955832828214137.md</MDResultFile>
  </PnPTestSummary>
  <PnPTestSummary>
    <PnPConfigurationToTest>OnPremAppOnly</PnPConfigurationToTest>
    <TestDate>Wednesday, April 6, 2016</TestDate>
    <TestTime>9:25 PM</TestTime>
    <PnPBranch>dev</PnPBranch>
    <VSBuildConfiguration>debug15</VSBuildConfiguration>
    <NumberOfTests>295</NumberOfTests>
    <ElapsedTime>0h 21m 57s</ElapsedTime>
    <FailedTests>3</FailedTests>
    <SkippedTests>51</SkippedTests>
    <PassedTests>241</PassedTests>
    <MDResultFile>c:\pnpbuildtemp\PnPUnitTestResults-20160406-OnPremAppOnly-635955819240042321.md</MDResultFile>
  </PnPTestSummary>
  <PnPTestSummary>
    <PnPConfigurationToTest>OnPremCred</PnPConfigurationToTest>
    <TestDate>Wednesday, April 6, 2016</TestDate>
    <TestTime>9:00 PM</TestTime>
    <PnPBranch>dev</PnPBranch>
    <VSBuildConfiguration>debug15</VSBuildConfiguration>
    <NumberOfTests>295</NumberOfTests>
    <ElapsedTime>0h 24m 9s</ElapsedTime>
    <FailedTests>3</FailedTests>
    <SkippedTests>21</SkippedTests>
    <PassedTests>271</PassedTests>
    <MDResultFile>c:\pnpbuildtemp\PnPUnitTestResults-20160406-OnPremCred-635955804485107962.md</MDResultFile>
  </PnPTestSummary>
  <PnPTestSummary>
    <PnPConfigurationToTest>OnlineAppOnly</PnPConfigurationToTest>
    <TestDate>Tuesday, April 5, 2016</TestDate>
    <TestTime>10:36 PM</TestTime>
    <PnPBranch>dev</PnPBranch>
    <VSBuildConfiguration>debug</VSBuildConfiguration>
    <NumberOfTests>301</NumberOfTests>
    <ElapsedTime>0h 40m 29s</ElapsedTime>
    <FailedTests>3</FailedTests>
    <SkippedTests>39</SkippedTests>
    <PassedTests>259</PassedTests>
    <MDResultFile>c:\pnpbuildtemp\PnPUnitTestResults-20160405-OnlineAppOnly-635954133880386935.md</MDResultFile>
  </PnPTestSummary>
  <PnPTestSummary>
    <PnPConfigurationToTest>OnlineCred</PnPConfigurationToTest>
    <TestDate>Monday, April 4, 2016</TestDate>
    <TestTime>9:47 PM</TestTime>
    <PnPBranch>dev</PnPBranch>
    <VSBuildConfiguration>debug</VSBuildConfiguration>
    <NumberOfTests>301</NumberOfTests>
    <ElapsedTime>0h 48m 29s</ElapsedTime>
    <FailedTests>3</FailedTests>
    <SkippedTests>7</SkippedTests>
    <PassedTests>291</PassedTests>
    <MDResultFile>c:\pnpbuildtemp\PnPUnitTestResults-20160404-OnlineCred-635954104491259609.md</MDResultFile>
  </PnPTestSummary>
  <PnPTestSummary>
    <PnPConfigurationToTest>OnPremAppOnly</PnPConfigurationToTest>
    <TestDate>Monday, April 4, 2016</TestDate>
    <TestTime>9:25 PM</TestTime>
    <PnPBranch>dev</PnPBranch>
    <VSBuildConfiguration>debug15</VSBuildConfiguration>
    <NumberOfTests>293</NumberOfTests>
    <ElapsedTime>0h 21m 22s</ElapsedTime>
    <FailedTests>3</FailedTests>
    <SkippedTests>51</SkippedTests>
    <PassedTests>239</PassedTests>
    <MDResultFile>c:\pnpbuildtemp\PnPUnitTestResults-20160404-OnPremAppOnly-635954091175732971.md</MDResultFile>
  </PnPTestSummary>
  <PnPTestSummary>
    <PnPConfigurationToTest>OnPremCred</PnPConfigurationToTest>
    <TestDate>Monday, April 4, 2016</TestDate>
    <TestTime>9:00 PM</TestTime>
    <PnPBranch>dev</PnPBranch>
    <VSBuildConfiguration>debug15</VSBuildConfiguration>
    <NumberOfTests>293</NumberOfTests>
    <ElapsedTime>0h 24m 5s</ElapsedTime>
    <FailedTests>3</FailedTests>
    <SkippedTests>21</SkippedTests>
    <PassedTests>269</PassedTests>
    <MDResultFile>c:\pnpbuildtemp\PnPUnitTestResults-20160404-OnPremCred-635954076475540590.md</MDResultFile>
  </PnPTestSummary>
  <PnPTestSummary>
    <PnPConfigurationToTest>OnlineAppOnly</PnPConfigurationToTest>
    <TestDate>Monday, April 4, 2016</TestDate>
    <TestTime>10:31 PM</TestTime>
    <PnPBranch>dev</PnPBranch>
    <VSBuildConfiguration>debug</VSBuildConfiguration>
    <NumberOfTests>301</NumberOfTests>
    <ElapsedTime>0h 40m 51s</ElapsedTime>
    <FailedTests>3</FailedTests>
    <SkippedTests>39</SkippedTests>
    <PassedTests>259</PassedTests>
    <MDResultFile>c:\pnpbuildtemp\PnPUnitTestResults-20160404-OnlineAppOnly-635953266649370922.md</MDResultFile>
  </PnPTestSummary>
  <PnPTestSummary>
    <PnPConfigurationToTest>OnlineCred</PnPConfigurationToTest>
    <TestDate>Sunday, April 3, 2016</TestDate>
    <TestTime>9:47 PM</TestTime>
    <PnPBranch>dev</PnPBranch>
    <VSBuildConfiguration>debug</VSBuildConfiguration>
    <NumberOfTests>301</NumberOfTests>
    <ElapsedTime>0h 43m 11s</ElapsedTime>
    <FailedTests>3</FailedTests>
    <SkippedTests>7</SkippedTests>
    <PassedTests>291</PassedTests>
    <MDResultFile>c:\pnpbuildtemp\PnPUnitTestResults-20160403-OnlineCred-635953240483468426.md</MDResultFile>
  </PnPTestSummary>
  <PnPTestSummary>
    <PnPConfigurationToTest>OnPremAppOnly</PnPConfigurationToTest>
    <TestDate>Sunday, April 3, 2016</TestDate>
    <TestTime>9:25 PM</TestTime>
    <PnPBranch>dev</PnPBranch>
    <VSBuildConfiguration>debug15</VSBuildConfiguration>
    <NumberOfTests>293</NumberOfTests>
    <ElapsedTime>0h 21m 41s</ElapsedTime>
    <FailedTests>3</FailedTests>
    <SkippedTests>51</SkippedTests>
    <PassedTests>239</PassedTests>
    <MDResultFile>c:\pnpbuildtemp\PnPUnitTestResults-20160403-OnPremAppOnly-635953227012032566.md</MDResultFile>
  </PnPTestSummary>
  <PnPTestSummary>
    <PnPConfigurationToTest>OnPremCred</PnPConfigurationToTest>
    <TestDate>Sunday, April 3, 2016</TestDate>
    <TestTime>9:00 PM</TestTime>
    <PnPBranch>dev</PnPBranch>
    <VSBuildConfiguration>debug15</VSBuildConfiguration>
    <NumberOfTests>293</NumberOfTests>
    <ElapsedTime>0h 23m 50s</ElapsedTime>
    <FailedTests>3</FailedTests>
    <SkippedTests>21</SkippedTests>
    <PassedTests>269</PassedTests>
    <MDResultFile>c:\pnpbuildtemp\PnPUnitTestResults-20160403-OnPremCred-635953212459972200.md</MDResultFile>
  </PnPTestSummary>
  <PnPTestSummary>
    <PnPConfigurationToTest>OnlineAppOnly</PnPConfigurationToTest>
    <TestDate>Sunday, April 3, 2016</TestDate>
    <TestTime>10:30 PM</TestTime>
    <PnPBranch>dev</PnPBranch>
    <VSBuildConfiguration>debug</VSBuildConfiguration>
    <NumberOfTests>301</NumberOfTests>
    <ElapsedTime>0h 36m 30s</ElapsedTime>
    <FailedTests>4</FailedTests>
    <SkippedTests>39</SkippedTests>
    <PassedTests>258</PassedTests>
    <MDResultFile>c:\pnpbuildtemp\PnPUnitTestResults-20160403-OnlineAppOnly-635952402060203557.md</MDResultFile>
  </PnPTestSummary>
  <PnPTestSummary>
    <PnPConfigurationToTest>OnlineCred</PnPConfigurationToTest>
    <TestDate>Saturday, April 2, 2016</TestDate>
    <TestTime>9:46 PM</TestTime>
    <PnPBranch>dev</PnPBranch>
    <VSBuildConfiguration>debug</VSBuildConfiguration>
    <NumberOfTests>301</NumberOfTests>
    <ElapsedTime>0h 43m 2s</ElapsedTime>
    <FailedTests>3</FailedTests>
    <SkippedTests>7</SkippedTests>
    <PassedTests>291</PassedTests>
    <MDResultFile>c:\pnpbuildtemp\PnPUnitTestResults-20160402-OnlineCred-635952375981514802.md</MDResultFile>
  </PnPTestSummary>
  <PnPTestSummary>
    <PnPConfigurationToTest>OnPremAppOnly</PnPConfigurationToTest>
    <TestDate>Saturday, April 2, 2016</TestDate>
    <TestTime>9:24 PM</TestTime>
    <PnPBranch>dev</PnPBranch>
    <VSBuildConfiguration>debug15</VSBuildConfiguration>
    <NumberOfTests>293</NumberOfTests>
    <ElapsedTime>0h 21m 46s</ElapsedTime>
    <FailedTests>3</FailedTests>
    <SkippedTests>51</SkippedTests>
    <PassedTests>239</PassedTests>
    <MDResultFile>c:\pnpbuildtemp\PnPUnitTestResults-20160402-OnPremAppOnly-635952362639865729.md</MDResultFile>
  </PnPTestSummary>
  <PnPTestSummary>
    <PnPConfigurationToTest>OnPremCred</PnPConfigurationToTest>
    <TestDate>Saturday, April 2, 2016</TestDate>
    <TestTime>9:00 PM</TestTime>
    <PnPBranch>dev</PnPBranch>
    <VSBuildConfiguration>debug15</VSBuildConfiguration>
    <NumberOfTests>293</NumberOfTests>
    <ElapsedTime>0h 23m 32s</ElapsedTime>
    <FailedTests>3</FailedTests>
    <SkippedTests>21</SkippedTests>
    <PassedTests>269</PassedTests>
    <MDResultFile>c:\pnpbuildtemp\PnPUnitTestResults-20160402-OnPremCred-635952348257963267.md</MDResultFile>
  </PnPTestSummary>
  <PnPTestSummary>
    <PnPConfigurationToTest>OnlineAppOnly</PnPConfigurationToTest>
    <TestDate>Saturday, April 2, 2016</TestDate>
    <TestTime>10:31 PM</TestTime>
    <PnPBranch>dev</PnPBranch>
    <VSBuildConfiguration>debug</VSBuildConfiguration>
    <NumberOfTests>301</NumberOfTests>
    <ElapsedTime>0h 58m 40s</ElapsedTime>
    <FailedTests>2</FailedTests>
    <SkippedTests>39</SkippedTests>
    <PassedTests>260</PassedTests>
    <MDResultFile>c:\pnpbuildtemp\PnPUnitTestResults-20160402-OnlineAppOnly-635951538803985372.md</MDResultFile>
  </PnPTestSummary>
  <PnPTestSummary>
    <PnPConfigurationToTest>OnlineCred</PnPConfigurationToTest>
    <TestDate>Friday, April 1, 2016</TestDate>
    <TestTime>9:46 PM</TestTime>
    <PnPBranch>dev</PnPBranch>
    <VSBuildConfiguration>debug</VSBuildConfiguration>
    <NumberOfTests>301</NumberOfTests>
    <ElapsedTime>0h 44m 1s</ElapsedTime>
    <FailedTests>3</FailedTests>
    <SkippedTests>7</SkippedTests>
    <PassedTests>291</PassedTests>
    <MDResultFile>c:\pnpbuildtemp\PnPUnitTestResults-20160401-OnlineCred-635951512145590433.md</MDResultFile>
  </PnPTestSummary>
  <PnPTestSummary>
    <PnPConfigurationToTest>OnPremAppOnly</PnPConfigurationToTest>
    <TestDate>Friday, April 1, 2016</TestDate>
    <TestTime>9:24 PM</TestTime>
    <PnPBranch>dev</PnPBranch>
    <VSBuildConfiguration>debug15</VSBuildConfiguration>
    <NumberOfTests>293</NumberOfTests>
    <ElapsedTime>0h 22m 9s</ElapsedTime>
    <FailedTests>3</FailedTests>
    <SkippedTests>51</SkippedTests>
    <PassedTests>239</PassedTests>
    <MDResultFile>c:\pnpbuildtemp\PnPUnitTestResults-20160401-OnPremAppOnly-635951498598341229.md</MDResultFile>
  </PnPTestSummary>
  <PnPTestSummary>
    <PnPConfigurationToTest>OnPremCred</PnPConfigurationToTest>
    <TestDate>Friday, April 1, 2016</TestDate>
    <TestTime>9:00 PM</TestTime>
    <PnPBranch>dev</PnPBranch>
    <VSBuildConfiguration>debug15</VSBuildConfiguration>
    <NumberOfTests>293</NumberOfTests>
    <ElapsedTime>0h 23m 28s</ElapsedTime>
    <FailedTests>3</FailedTests>
    <SkippedTests>21</SkippedTests>
    <PassedTests>269</PassedTests>
    <MDResultFile>c:\pnpbuildtemp\PnPUnitTestResults-20160401-OnPremCred-635951484269981003.md</MDResultFile>
  </PnPTestSummary>
  <PnPTestSummary>
    <PnPConfigurationToTest>OnlineAppOnly</PnPConfigurationToTest>
    <TestDate>Friday, April 1, 2016</TestDate>
    <TestTime>10:43 PM</TestTime>
    <PnPBranch>dev</PnPBranch>
    <VSBuildConfiguration>debug</VSBuildConfiguration>
    <NumberOfTests>301</NumberOfTests>
    <ElapsedTime>0h 40m 47s</ElapsedTime>
    <FailedTests>4</FailedTests>
    <SkippedTests>39</SkippedTests>
    <PassedTests>258</PassedTests>
    <MDResultFile>c:\pnpbuildtemp\PnPUnitTestResults-20160401-OnlineAppOnly-635950682391700273.md</MDResultFile>
  </PnPTestSummary>
  <PnPTestSummary>
    <PnPConfigurationToTest>OnlineCred</PnPConfigurationToTest>
    <TestDate>Thursday, March 31, 2016</TestDate>
    <TestTime>9:47 PM</TestTime>
    <PnPBranch>dev</PnPBranch>
    <VSBuildConfiguration>debug</VSBuildConfiguration>
    <NumberOfTests>301</NumberOfTests>
    <ElapsedTime>0h 56m 12s</ElapsedTime>
    <FailedTests>3</FailedTests>
    <SkippedTests>7</SkippedTests>
    <PassedTests>291</PassedTests>
    <MDResultFile>c:\pnpbuildtemp\PnPUnitTestResults-20160331-OnlineCred-635950648418229359.md</MDResultFile>
  </PnPTestSummary>
  <PnPTestSummary>
    <PnPConfigurationToTest>OnPremAppOnly</PnPConfigurationToTest>
    <TestDate>Thursday, March 31, 2016</TestDate>
    <TestTime>9:24 PM</TestTime>
    <PnPBranch>dev</PnPBranch>
    <VSBuildConfiguration>debug15</VSBuildConfiguration>
    <NumberOfTests>293</NumberOfTests>
    <ElapsedTime>0h 22m 12s</ElapsedTime>
    <FailedTests>3</FailedTests>
    <SkippedTests>51</SkippedTests>
    <PassedTests>239</PassedTests>
    <MDResultFile>c:\pnpbuildtemp\PnPUnitTestResults-20160331-OnPremAppOnly-635950634853054288.md</MDResultFile>
  </PnPTestSummary>
  <PnPTestSummary>
    <PnPConfigurationToTest>OnPremCred</PnPConfigurationToTest>
    <TestDate>Thursday, March 31, 2016</TestDate>
    <TestTime>9:00 PM</TestTime>
    <PnPBranch>dev</PnPBranch>
    <VSBuildConfiguration>debug15</VSBuildConfiguration>
    <NumberOfTests>293</NumberOfTests>
    <ElapsedTime>0h 23m 49s</ElapsedTime>
    <FailedTests>3</FailedTests>
    <SkippedTests>21</SkippedTests>
    <PassedTests>269</PassedTests>
    <MDResultFile>c:\pnpbuildtemp\PnPUnitTestResults-20160331-OnPremCred-635950620309967643.md</MDResultFile>
  </PnPTestSummary>
  <PnPTestSummary>
    <PnPConfigurationToTest>OnlineAppOnly</PnPConfigurationToTest>
    <TestDate>Thursday, March 31, 2016</TestDate>
    <TestTime>10:36 PM</TestTime>
    <PnPBranch>dev</PnPBranch>
    <VSBuildConfiguration>debug</VSBuildConfiguration>
    <NumberOfTests>301</NumberOfTests>
    <ElapsedTime>0h 47m 59s</ElapsedTime>
    <FailedTests>3</FailedTests>
    <SkippedTests>39</SkippedTests>
    <PassedTests>259</PassedTests>
    <MDResultFile>c:\pnpbuildtemp\PnPUnitTestResults-20160331-OnlineAppOnly-635949813816985854.md</MDResultFile>
  </PnPTestSummary>
  <PnPTestSummary>
    <PnPConfigurationToTest>OnlineCred</PnPConfigurationToTest>
    <TestDate>Wednesday, March 30, 2016</TestDate>
    <TestTime>9:46 PM</TestTime>
    <PnPBranch>dev</PnPBranch>
    <VSBuildConfiguration>debug</VSBuildConfiguration>
    <NumberOfTests>301</NumberOfTests>
    <ElapsedTime>0h 49m 12s</ElapsedTime>
    <FailedTests>2</FailedTests>
    <SkippedTests>7</SkippedTests>
    <PassedTests>292</PassedTests>
    <MDResultFile>c:\pnpbuildtemp\PnPUnitTestResults-20160330-OnlineCred-635949783844839411.md</MDResultFile>
  </PnPTestSummary>
  <PnPTestSummary>
    <PnPConfigurationToTest>OnPremAppOnly</PnPConfigurationToTest>
    <TestDate>Wednesday, March 30, 2016</TestDate>
    <TestTime>9:24 PM</TestTime>
    <PnPBranch>dev</PnPBranch>
    <VSBuildConfiguration>debug15</VSBuildConfiguration>
    <NumberOfTests>293</NumberOfTests>
    <ElapsedTime>0h 21m 30s</ElapsedTime>
    <FailedTests>3</FailedTests>
    <SkippedTests>51</SkippedTests>
    <PassedTests>239</PassedTests>
    <MDResultFile>c:\pnpbuildtemp\PnPUnitTestResults-20160330-OnPremAppOnly-635949770664492202.md</MDResultFile>
  </PnPTestSummary>
  <PnPTestSummary>
    <PnPConfigurationToTest>OnPremCred</PnPConfigurationToTest>
    <TestDate>Wednesday, March 30, 2016</TestDate>
    <TestTime>9:00 PM</TestTime>
    <PnPBranch>dev</PnPBranch>
    <VSBuildConfiguration>debug15</VSBuildConfiguration>
    <NumberOfTests>293</NumberOfTests>
    <ElapsedTime>0h 23m 23s</ElapsedTime>
    <FailedTests>3</FailedTests>
    <SkippedTests>21</SkippedTests>
    <PassedTests>269</PassedTests>
    <MDResultFile>c:\pnpbuildtemp\PnPUnitTestResults-20160330-OnPremCred-635949756377841816.md</MDResultFile>
  </PnPTestSummary>
  <PnPTestSummary>
    <PnPConfigurationToTest>OnlineAppOnly</PnPConfigurationToTest>
    <TestDate>Wednesday, March 30, 2016</TestDate>
    <TestTime>10:40 PM</TestTime>
    <PnPBranch>dev</PnPBranch>
    <VSBuildConfiguration>debug</VSBuildConfiguration>
    <NumberOfTests>301</NumberOfTests>
    <ElapsedTime>0h 43m 20s</ElapsedTime>
    <FailedTests>4</FailedTests>
    <SkippedTests>39</SkippedTests>
    <PassedTests>258</PassedTests>
    <MDResultFile>c:\pnpbuildtemp\PnPUnitTestResults-20160330-OnlineAppOnly-635948952463654045.md</MDResultFile>
  </PnPTestSummary>
  <PnPTestSummary>
    <PnPConfigurationToTest>OnlineCred</PnPConfigurationToTest>
    <TestDate>Tuesday, March 29, 2016</TestDate>
    <TestTime>9:46 PM</TestTime>
    <PnPBranch>dev</PnPBranch>
    <VSBuildConfiguration>debug</VSBuildConfiguration>
    <NumberOfTests>301</NumberOfTests>
    <ElapsedTime>0h 54m 12s</ElapsedTime>
    <FailedTests>3</FailedTests>
    <SkippedTests>7</SkippedTests>
    <PassedTests>291</PassedTests>
    <MDResultFile>c:\pnpbuildtemp\PnPUnitTestResults-20160329-OnlineCred-635948919685044697.md</MDResultFile>
  </PnPTestSummary>
  <PnPTestSummary>
    <PnPConfigurationToTest>OnPremAppOnly</PnPConfigurationToTest>
    <TestDate>Tuesday, March 29, 2016</TestDate>
    <TestTime>9:24 PM</TestTime>
    <PnPBranch>dev</PnPBranch>
    <VSBuildConfiguration>debug15</VSBuildConfiguration>
    <NumberOfTests>293</NumberOfTests>
    <ElapsedTime>0h 21m 13s</ElapsedTime>
    <FailedTests>3</FailedTests>
    <SkippedTests>51</SkippedTests>
    <PassedTests>239</PassedTests>
    <MDResultFile>c:\pnpbuildtemp\PnPUnitTestResults-20160329-OnPremAppOnly-635948906708008401.md</MDResultFile>
  </PnPTestSummary>
  <PnPTestSummary>
    <PnPConfigurationToTest>OnPremCred</PnPConfigurationToTest>
    <TestDate>Tuesday, March 29, 2016</TestDate>
    <TestTime>9:00 PM</TestTime>
    <PnPBranch>dev</PnPBranch>
    <VSBuildConfiguration>debug15</VSBuildConfiguration>
    <NumberOfTests>293</NumberOfTests>
    <ElapsedTime>0h 23m 36s</ElapsedTime>
    <FailedTests>3</FailedTests>
    <SkippedTests>21</SkippedTests>
    <PassedTests>269</PassedTests>
    <MDResultFile>c:\pnpbuildtemp\PnPUnitTestResults-20160329-OnPremCred-635948892294348094.md</MDResultFile>
  </PnPTestSummary>
  <PnPTestSummary>
    <PnPConfigurationToTest>OnlineAppOnly</PnPConfigurationToTest>
    <TestDate>Tuesday, March 29, 2016</TestDate>
    <TestTime>11:04 PM</TestTime>
    <PnPBranch>dev</PnPBranch>
    <VSBuildConfiguration>debug</VSBuildConfiguration>
    <NumberOfTests>301</NumberOfTests>
    <ElapsedTime>0h 43m 43s</ElapsedTime>
    <FailedTests>3</FailedTests>
    <SkippedTests>39</SkippedTests>
    <PassedTests>259</PassedTests>
    <MDResultFile>c:\pnpbuildtemp\PnPUnitTestResults-20160329-OnlineAppOnly-635948102619318197.md</MDResultFile>
  </PnPTestSummary>
  <PnPTestSummary>
    <PnPConfigurationToTest>OnlineCred</PnPConfigurationToTest>
    <TestDate>Monday, March 28, 2016</TestDate>
    <TestTime>9:46 PM</TestTime>
    <PnPBranch>dev</PnPBranch>
    <VSBuildConfiguration>debug</VSBuildConfiguration>
    <NumberOfTests>301</NumberOfTests>
    <ElapsedTime>1h 17m 31s</ElapsedTime>
    <FailedTests>3</FailedTests>
    <SkippedTests>7</SkippedTests>
    <PassedTests>291</PassedTests>
    <MDResultFile>c:\pnpbuildtemp\PnPUnitTestResults-20160328-OnlineCred-635948055853105258.md</MDResultFile>
  </PnPTestSummary>
  <PnPTestSummary>
    <PnPConfigurationToTest>OnPremAppOnly</PnPConfigurationToTest>
    <TestDate>Monday, March 28, 2016</TestDate>
    <TestTime>9:24 PM</TestTime>
    <PnPBranch>dev</PnPBranch>
    <VSBuildConfiguration>debug15</VSBuildConfiguration>
    <NumberOfTests>293</NumberOfTests>
    <ElapsedTime>0h 21m 17s</ElapsedTime>
    <FailedTests>3</FailedTests>
    <SkippedTests>51</SkippedTests>
    <PassedTests>239</PassedTests>
    <MDResultFile>c:\pnpbuildtemp\PnPUnitTestResults-20160328-OnPremAppOnly-635948042828033929.md</MDResultFile>
  </PnPTestSummary>
  <PnPTestSummary>
    <PnPConfigurationToTest>OnPremCred</PnPConfigurationToTest>
    <TestDate>Monday, March 28, 2016</TestDate>
    <TestTime>9:00 PM</TestTime>
    <PnPBranch>dev</PnPBranch>
    <VSBuildConfiguration>debug15</VSBuildConfiguration>
    <NumberOfTests>293</NumberOfTests>
    <ElapsedTime>0h 23m 44s</ElapsedTime>
    <FailedTests>3</FailedTests>
    <SkippedTests>21</SkippedTests>
    <PassedTests>269</PassedTests>
    <MDResultFile>c:\pnpbuildtemp\PnPUnitTestResults-20160328-OnPremCred-635948028333634430.md</MDResultFile>
  </PnPTestSummary>
  <PnPTestSummary>
    <PnPConfigurationToTest>OnlineAppOnly</PnPConfigurationToTest>
    <TestDate>Monday, March 28, 2016</TestDate>
    <TestTime>10:42 PM</TestTime>
    <PnPBranch>dev</PnPBranch>
    <VSBuildConfiguration>debug</VSBuildConfiguration>
    <NumberOfTests>301</NumberOfTests>
    <ElapsedTime>1h 31m 44s</ElapsedTime>
    <FailedTests>4</FailedTests>
    <SkippedTests>39</SkippedTests>
    <PassedTests>258</PassedTests>
    <MDResultFile>c:\pnpbuildtemp\PnPUnitTestResults-20160328-OnlineAppOnly-635947225217726204.md</MDResultFile>
  </PnPTestSummary>
  <PnPTestSummary>
    <PnPConfigurationToTest>OnlineCred</PnPConfigurationToTest>
    <TestDate>Sunday, March 27, 2016</TestDate>
    <TestTime>9:46 PM</TestTime>
    <PnPBranch>dev</PnPBranch>
    <VSBuildConfiguration>debug</VSBuildConfiguration>
    <NumberOfTests>301</NumberOfTests>
    <ElapsedTime>0h 55m 27s</ElapsedTime>
    <FailedTests>3</FailedTests>
    <SkippedTests>7</SkippedTests>
    <PassedTests>291</PassedTests>
    <MDResultFile>c:\pnpbuildtemp\PnPUnitTestResults-20160327-OnlineCred-635947191687387819.md</MDResultFile>
  </PnPTestSummary>
  <PnPTestSummary>
    <PnPConfigurationToTest>OnPremAppOnly</PnPConfigurationToTest>
    <TestDate>Sunday, March 27, 2016</TestDate>
    <TestTime>9:24 PM</TestTime>
    <PnPBranch>dev</PnPBranch>
    <VSBuildConfiguration>debug15</VSBuildConfiguration>
    <NumberOfTests>293</NumberOfTests>
    <ElapsedTime>0h 21m 15s</ElapsedTime>
    <FailedTests>3</FailedTests>
    <SkippedTests>51</SkippedTests>
    <PassedTests>239</PassedTests>
    <MDResultFile>c:\pnpbuildtemp\PnPUnitTestResults-20160327-OnPremAppOnly-635947178678966190.md</MDResultFile>
  </PnPTestSummary>
  <PnPTestSummary>
    <PnPConfigurationToTest>OnPremCred</PnPConfigurationToTest>
    <TestDate>Sunday, March 27, 2016</TestDate>
    <TestTime>9:00 PM</TestTime>
    <PnPBranch>dev</PnPBranch>
    <VSBuildConfiguration>debug15</VSBuildConfiguration>
    <NumberOfTests>293</NumberOfTests>
    <ElapsedTime>0h 23m 36s</ElapsedTime>
    <FailedTests>3</FailedTests>
    <SkippedTests>21</SkippedTests>
    <PassedTests>269</PassedTests>
    <MDResultFile>c:\pnpbuildtemp\PnPUnitTestResults-20160327-OnPremCred-635947164256561506.md</MDResultFile>
  </PnPTestSummary>
  <PnPTestSummary>
    <PnPConfigurationToTest>OnlineAppOnly</PnPConfigurationToTest>
    <TestDate>Sunday, March 27, 2016</TestDate>
    <TestTime>12:33 AM</TestTime>
    <PnPBranch>dev</PnPBranch>
    <VSBuildConfiguration>debug</VSBuildConfiguration>
    <NumberOfTests>301</NumberOfTests>
    <ElapsedTime>2h 0m 15s</ElapsedTime>
    <FailedTests>2</FailedTests>
    <SkippedTests>39</SkippedTests>
    <PassedTests>260</PassedTests>
    <MDResultFile>c:\pnpbuildtemp\PnPUnitTestResults-20160327-OnlineAppOnly-635946391952900082.md</MDResultFile>
  </PnPTestSummary>
  <PnPTestSummary>
    <PnPConfigurationToTest>OnlineCred</PnPConfigurationToTest>
    <TestDate>Saturday, March 26, 2016</TestDate>
    <TestTime>10:50 PM</TestTime>
    <PnPBranch>dev</PnPBranch>
    <VSBuildConfiguration>debug</VSBuildConfiguration>
    <NumberOfTests>301</NumberOfTests>
    <ElapsedTime>1h 42m 31s</ElapsedTime>
    <FailedTests>2</FailedTests>
    <SkippedTests>7</SkippedTests>
    <PassedTests>292</PassedTests>
    <MDResultFile>c:\pnpbuildtemp\PnPUnitTestResults-20160326-OnlineCred-635946330253635907.md</MDResultFile>
  </PnPTestSummary>
  <PnPTestSummary>
    <PnPConfigurationToTest>OnPremAppOnly</PnPConfigurationToTest>
    <TestDate>Saturday, March 26, 2016</TestDate>
    <TestTime>10:23 PM</TestTime>
    <PnPBranch>dev</PnPBranch>
    <VSBuildConfiguration>debug15</VSBuildConfiguration>
    <NumberOfTests>293</NumberOfTests>
    <ElapsedTime>0h 26m 6s</ElapsedTime>
    <FailedTests>3</FailedTests>
    <SkippedTests>51</SkippedTests>
    <PassedTests>239</PassedTests>
    <MDResultFile>c:\pnpbuildtemp\PnPUnitTestResults-20160326-OnPremAppOnly-635946314264662073.md</MDResultFile>
  </PnPTestSummary>
  <PnPTestSummary>
    <PnPConfigurationToTest>OnPremCred</PnPConfigurationToTest>
    <TestDate>Saturday, March 26, 2016</TestDate>
    <TestTime>10:00 PM</TestTime>
    <PnPBranch>dev</PnPBranch>
    <VSBuildConfiguration>debug15</VSBuildConfiguration>
    <NumberOfTests>293</NumberOfTests>
    <ElapsedTime>0h 22m 55s</ElapsedTime>
    <FailedTests>3</FailedTests>
    <SkippedTests>21</SkippedTests>
    <PassedTests>269</PassedTests>
    <MDResultFile>c:\pnpbuildtemp\PnPUnitTestResults-20160326-OnPremCred-635946300265869961.md</MDResultFile>
  </PnPTestSummary>
  <PnPTestSummary>
    <PnPConfigurationToTest>OnlineAppOnly</PnPConfigurationToTest>
    <TestDate>Saturday, March 26, 2016</TestDate>
    <TestTime>11:49 PM</TestTime>
    <PnPBranch>dev</PnPBranch>
    <VSBuildConfiguration>debug</VSBuildConfiguration>
    <NumberOfTests>301</NumberOfTests>
    <ElapsedTime>1h 4m 12s</ElapsedTime>
    <FailedTests>3</FailedTests>
    <SkippedTests>39</SkippedTests>
    <PassedTests>259</PassedTests>
    <MDResultFile>c:\pnpbuildtemp\PnPUnitTestResults-20160326-OnlineAppOnly-635945501564114577.md</MDResultFile>
  </PnPTestSummary>
  <PnPTestSummary>
    <PnPConfigurationToTest>OnlineCred</PnPConfigurationToTest>
    <TestDate>Friday, March 25, 2016</TestDate>
    <TestTime>10:45 PM</TestTime>
    <PnPBranch>dev</PnPBranch>
    <VSBuildConfiguration>debug</VSBuildConfiguration>
    <NumberOfTests>301</NumberOfTests>
    <ElapsedTime>1h 2m 59s</ElapsedTime>
    <FailedTests>2</FailedTests>
    <SkippedTests>7</SkippedTests>
    <PassedTests>292</PassedTests>
    <MDResultFile>c:\pnpbuildtemp\PnPUnitTestResults-20160325-OnlineCred-635945463526870248.md</MDResultFile>
  </PnPTestSummary>
  <PnPTestSummary>
    <PnPConfigurationToTest>OnPremAppOnly</PnPConfigurationToTest>
    <TestDate>Friday, March 25, 2016</TestDate>
    <TestTime>10:23 PM</TestTime>
    <PnPBranch>dev</PnPBranch>
    <VSBuildConfiguration>debug15</VSBuildConfiguration>
    <NumberOfTests>293</NumberOfTests>
    <ElapsedTime>0h 21m 36s</ElapsedTime>
    <FailedTests>3</FailedTests>
    <SkippedTests>51</SkippedTests>
    <PassedTests>239</PassedTests>
    <MDResultFile>c:\pnpbuildtemp\PnPUnitTestResults-20160325-OnPremAppOnly-635945450303650430.md</MDResultFile>
  </PnPTestSummary>
  <PnPTestSummary>
    <PnPConfigurationToTest>OnPremCred</PnPConfigurationToTest>
    <TestDate>Friday, March 25, 2016</TestDate>
    <TestTime>10:00 PM</TestTime>
    <PnPBranch>dev</PnPBranch>
    <VSBuildConfiguration>debug15</VSBuildConfiguration>
    <NumberOfTests>293</NumberOfTests>
    <ElapsedTime>0h 22m 58s</ElapsedTime>
    <FailedTests>3</FailedTests>
    <SkippedTests>21</SkippedTests>
    <PassedTests>269</PassedTests>
    <MDResultFile>c:\pnpbuildtemp\PnPUnitTestResults-20160325-OnPremCred-635945436275832039.md</MDResultFile>
  </PnPTestSummary>
  <PnPTestSummary>
    <PnPConfigurationToTest>OnlineAppOnly</PnPConfigurationToTest>
    <TestDate>Thursday, March 24, 2016</TestDate>
    <TestTime>10:50 PM</TestTime>
    <PnPBranch>dev</PnPBranch>
    <VSBuildConfiguration>debug</VSBuildConfiguration>
    <NumberOfTests>301</NumberOfTests>
    <ElapsedTime>0h 41m 13s</ElapsedTime>
    <FailedTests>3</FailedTests>
    <SkippedTests>39</SkippedTests>
    <PassedTests>259</PassedTests>
    <MDResultFile>c:\pnpbuildtemp\PnPUnitTestResults-20160324-OnlineAppOnly-635944602301125122.md</MDResultFile>
  </PnPTestSummary>
  <PnPTestSummary>
    <PnPConfigurationToTest>OnlineCred</PnPConfigurationToTest>
    <TestDate>Thursday, March 24, 2016</TestDate>
    <TestTime>10:01 PM</TestTime>
    <PnPBranch>dev</PnPBranch>
    <VSBuildConfiguration>debug</VSBuildConfiguration>
    <NumberOfTests>301</NumberOfTests>
    <ElapsedTime>0h 49m 0s</ElapsedTime>
    <FailedTests>2</FailedTests>
    <SkippedTests>7</SkippedTests>
    <PassedTests>292</PassedTests>
    <MDResultFile>c:\pnpbuildtemp\PnPUnitTestResults-20160324-OnlineCred-635944572643560142.md</MDResultFile>
  </PnPTestSummary>
  <PnPTestSummary>
    <PnPConfigurationToTest>OnlineAppOnly</PnPConfigurationToTest>
    <TestDate>Wednesday, March 23, 2016</TestDate>
    <TestTime>11:43 PM</TestTime>
    <PnPBranch>dev</PnPBranch>
    <VSBuildConfiguration>debug</VSBuildConfiguration>
    <NumberOfTests>301</NumberOfTests>
    <ElapsedTime>0h 50m 51s</ElapsedTime>
    <FailedTests>2</FailedTests>
    <SkippedTests>39</SkippedTests>
    <PassedTests>260</PassedTests>
    <MDResultFile>c:\pnpbuildtemp\PnPUnitTestResults-20160323-OnlineAppOnly-635942906067112562.md</MDResultFile>
  </PnPTestSummary>
  <PnPTestSummary>
    <PnPConfigurationToTest>OnlineCred</PnPConfigurationToTest>
    <TestDate>Tuesday, March 22, 2016</TestDate>
    <TestTime>10:48 PM</TestTime>
    <PnPBranch>dev</PnPBranch>
    <VSBuildConfiguration>debug</VSBuildConfiguration>
    <NumberOfTests>301</NumberOfTests>
    <ElapsedTime>0h 54m 42s</ElapsedTime>
    <FailedTests>2</FailedTests>
    <SkippedTests>7</SkippedTests>
    <PassedTests>292</PassedTests>
    <MDResultFile>c:\pnpbuildtemp\PnPUnitTestResults-20160322-OnlineCred-635942872984320192.md</MDResultFile>
  </PnPTestSummary>
  <PnPTestSummary>
    <PnPConfigurationToTest>OnPremAppOnly</PnPConfigurationToTest>
    <TestDate>Tuesday, March 22, 2016</TestDate>
    <TestTime>10:25 PM</TestTime>
    <PnPBranch>dev</PnPBranch>
    <VSBuildConfiguration>debug15</VSBuildConfiguration>
    <NumberOfTests>293</NumberOfTests>
    <ElapsedTime>0h 21m 37s</ElapsedTime>
    <FailedTests>3</FailedTests>
    <SkippedTests>51</SkippedTests>
    <PassedTests>239</PassedTests>
    <MDResultFile>c:\pnpbuildtemp\PnPUnitTestResults-20160322-OnPremAppOnly-635942859553543719.md</MDResultFile>
  </PnPTestSummary>
  <PnPTestSummary>
    <PnPConfigurationToTest>OnPremCred</PnPConfigurationToTest>
    <TestDate>Tuesday, March 22, 2016</TestDate>
    <TestTime>10:00 PM</TestTime>
    <PnPBranch>dev</PnPBranch>
    <VSBuildConfiguration>debug15</VSBuildConfiguration>
    <NumberOfTests>293</NumberOfTests>
    <ElapsedTime>0h 24m 41s</ElapsedTime>
    <FailedTests>3</FailedTests>
    <SkippedTests>21</SkippedTests>
    <PassedTests>269</PassedTests>
    <MDResultFile>c:\pnpbuildtemp\PnPUnitTestResults-20160322-OnPremCred-635942844487568836.md</MDResultFile>
  </PnPTestSummary>
  <PnPTestSummary>
    <PnPConfigurationToTest>OnlineAppOnly</PnPConfigurationToTest>
    <TestDate>Saturday, March 5, 2016</TestDate>
    <TestTime>11:23 PM</TestTime>
    <PnPBranch>dev</PnPBranch>
    <VSBuildConfiguration>debug</VSBuildConfiguration>
    <NumberOfTests>298</NumberOfTests>
    <ElapsedTime>0h 33m 26s</ElapsedTime>
    <FailedTests>5</FailedTests>
    <SkippedTests>39</SkippedTests>
    <PassedTests>254</PassedTests>
    <MDResultFile>c:\pnpbuildtemp\PnPUnitTestResults-20160305-OnlineAppOnly-635927342123936080.md</MDResultFile>
  </PnPTestSummary>
  <PnPTestSummary>
    <PnPConfigurationToTest>OnlineCred</PnPConfigurationToTest>
    <TestDate>Friday, March 4, 2016</TestDate>
    <TestTime>10:45 PM</TestTime>
    <PnPBranch>dev</PnPBranch>
    <VSBuildConfiguration>debug</VSBuildConfiguration>
    <NumberOfTests>298</NumberOfTests>
    <ElapsedTime>0h 37m 39s</ElapsedTime>
    <FailedTests>5</FailedTests>
    <SkippedTests>7</SkippedTests>
    <PassedTests>286</PassedTests>
    <MDResultFile>c:\pnpbuildtemp\PnPUnitTestResults-20160304-OnlineCred-635927319283293582.md</MDResultFile>
  </PnPTestSummary>
  <PnPTestSummary>
    <PnPConfigurationToTest>OnPremAppOnly</PnPConfigurationToTest>
    <TestDate>Friday, March 4, 2016</TestDate>
    <TestTime>10:23 PM</TestTime>
    <PnPBranch>dev</PnPBranch>
    <VSBuildConfiguration>debug15</VSBuildConfiguration>
    <NumberOfTests>290</NumberOfTests>
    <ElapsedTime>0h 21m 25s</ElapsedTime>
    <FailedTests>0</FailedTests>
    <SkippedTests>51</SkippedTests>
    <PassedTests>239</PassedTests>
    <MDResultFile>c:\pnpbuildtemp\PnPUnitTestResults-20160304-OnPremAppOnly-635927306196027430.md</MDResultFile>
  </PnPTestSummary>
</PnPUnitTestResults>