<PnPUnitTestResults>
  <PnPTestSummary>
    <PnPConfigurationToTest>OnlineAppOnly</PnPConfigurationToTest>
    <TestDate>Friday, March 4, 2016</TestDate>
    <TestTime>11:46 PM</TestTime>
    <PnPBranch>dev</PnPBranch>
    <VSBuildConfiguration>debug</VSBuildConfiguration>
    <NumberOfTests>298</NumberOfTests>
    <ElapsedTime>0h 47m 53s</ElapsedTime>
    <FailedTests>4</FailedTests>
    <SkippedTests>39</SkippedTests>
    <PassedTests>255</PassedTests>
    <MDResultFile>c:\pnpbuildtemp\PnPUnitTestResults-20160304-OnlineAppOnly-635926491855839734.md</MDResultFile>
  </PnPTestSummary>
  <PnPTestSummary>
    <PnPConfigurationToTest>OnlineCred</PnPConfigurationToTest>
    <TestDate>Thursday, March 3, 2016</TestDate>
    <TestTime>10:46 PM</TestTime>
    <PnPBranch>dev</PnPBranch>
    <VSBuildConfiguration>debug</VSBuildConfiguration>
    <NumberOfTests>298</NumberOfTests>
    <ElapsedTime>0h 59m 22s</ElapsedTime>
    <FailedTests>7</FailedTests>
    <SkippedTests>7</SkippedTests>
    <PassedTests>284</PassedTests>
    <MDResultFile>c:\pnpbuildtemp\PnPUnitTestResults-20160303-OnlineCred-635926455981091651.md</MDResultFile>
  </PnPTestSummary>
  <PnPTestSummary>
    <PnPConfigurationToTest>OnPremAppOnly</PnPConfigurationToTest>
    <TestDate>Thursday, March 3, 2016</TestDate>
    <TestTime>10:24 PM</TestTime>
    <PnPBranch>dev</PnPBranch>
    <VSBuildConfiguration>debug15</VSBuildConfiguration>
    <NumberOfTests>290</NumberOfTests>
    <ElapsedTime>0h 21m 41s</ElapsedTime>
    <FailedTests>0</FailedTests>
    <SkippedTests>51</SkippedTests>
    <PassedTests>239</PassedTests>
    <MDResultFile>c:\pnpbuildtemp\PnPUnitTestResults-20160303-OnPremAppOnly-635926442710772450.md</MDResultFile>
  </PnPTestSummary>
  <PnPTestSummary>
    <PnPConfigurationToTest>OnPremCred</PnPConfigurationToTest>
    <TestDate>Thursday, March 3, 2016</TestDate>
    <TestTime>10:00 PM</TestTime>
    <PnPBranch>dev</PnPBranch>
    <VSBuildConfiguration>debug15</VSBuildConfiguration>
    <NumberOfTests>290</NumberOfTests>
    <ElapsedTime>0h 23m 36s</ElapsedTime>
    <FailedTests>0</FailedTests>
    <SkippedTests>21</SkippedTests>
    <PassedTests>269</PassedTests>
    <MDResultFile>c:\pnpbuildtemp\PnPUnitTestResults-20160303-OnPremCred-635926428289460591.md</MDResultFile>
  </PnPTestSummary>
  <PnPTestSummary>
    <PnPConfigurationToTest>OnlineAppOnly</PnPConfigurationToTest>
    <TestDate>Thursday, March 3, 2016</TestDate>
    <TestTime>11:23 PM</TestTime>
    <PnPBranch>dev</PnPBranch>
    <VSBuildConfiguration>debug</VSBuildConfiguration>
    <NumberOfTests>294</NumberOfTests>
    <ElapsedTime>0h 36m 10s</ElapsedTime>
    <FailedTests>5</FailedTests>
    <SkippedTests>39</SkippedTests>
    <PassedTests>250</PassedTests>
    <MDResultFile>c:\pnpbuildtemp\PnPUnitTestResults-20160303-OnlineAppOnly-635925613931809071.md</MDResultFile>
  </PnPTestSummary>
  <PnPTestSummary>
    <PnPConfigurationToTest>OnlineCred</PnPConfigurationToTest>
    <TestDate>Wednesday, March 2, 2016</TestDate>
    <TestTime>10:46 PM</TestTime>
    <PnPBranch>dev</PnPBranch>
    <VSBuildConfiguration>debug</VSBuildConfiguration>
    <NumberOfTests>294</NumberOfTests>
    <ElapsedTime>0h 36m 42s</ElapsedTime>
    <FailedTests>6</FailedTests>
    <SkippedTests>7</SkippedTests>
    <PassedTests>281</PassedTests>
    <MDResultFile>c:\pnpbuildtemp\PnPUnitTestResults-20160302-OnlineCred-635925591661982905.md</MDResultFile>
  </PnPTestSummary>
  <PnPTestSummary>
    <PnPConfigurationToTest>OnPremAppOnly</PnPConfigurationToTest>
    <TestDate>Wednesday, March 2, 2016</TestDate>
    <TestTime>10:24 PM</TestTime>
    <PnPBranch>dev</PnPBranch>
    <VSBuildConfiguration>debug15</VSBuildConfiguration>
    <NumberOfTests>286</NumberOfTests>
    <ElapsedTime>0h 21m 31s</ElapsedTime>
    <FailedTests>0</FailedTests>
    <SkippedTests>51</SkippedTests>
    <PassedTests>235</PassedTests>
    <MDResultFile>c:\pnpbuildtemp\PnPUnitTestResults-20160302-OnPremAppOnly-635925578493683714.md</MDResultFile>
  </PnPTestSummary>
  <PnPTestSummary>
    <PnPConfigurationToTest>OnPremCred</PnPConfigurationToTest>
    <TestDate>Wednesday, March 2, 2016</TestDate>
    <TestTime>10:00 PM</TestTime>
    <PnPBranch>dev</PnPBranch>
    <VSBuildConfiguration>debug15</VSBuildConfiguration>
    <NumberOfTests>286</NumberOfTests>
    <ElapsedTime>0h 23m 18s</ElapsedTime>
    <FailedTests>0</FailedTests>
    <SkippedTests>21</SkippedTests>
    <PassedTests>265</PassedTests>
    <MDResultFile>c:\pnpbuildtemp\PnPUnitTestResults-20160302-OnPremCred-635925564257521955.md</MDResultFile>
  </PnPTestSummary>
  <PnPTestSummary>
    <PnPConfigurationToTest>OnlineAppOnly</PnPConfigurationToTest>
    <TestDate>Wednesday, March 2, 2016</TestDate>
    <TestTime>11:42 PM</TestTime>
    <PnPBranch>dev</PnPBranch>
    <VSBuildConfiguration>debug</VSBuildConfiguration>
    <NumberOfTests>294</NumberOfTests>
    <ElapsedTime>0h 46m 8s</ElapsedTime>
    <FailedTests>6</FailedTests>
    <SkippedTests>38</SkippedTests>
    <PassedTests>250</PassedTests>
    <MDResultFile>c:\pnpbuildtemp\PnPUnitTestResults-20160302-OnlineAppOnly-635924761456610114.md</MDResultFile>
  </PnPTestSummary>
  <PnPTestSummary>
    <PnPConfigurationToTest>OnlineCred</PnPConfigurationToTest>
    <TestDate>Tuesday, March 1, 2016</TestDate>
    <TestTime>10:45 PM</TestTime>
    <PnPBranch>dev</PnPBranch>
    <VSBuildConfiguration>debug</VSBuildConfiguration>
    <NumberOfTests>294</NumberOfTests>
    <ElapsedTime>0h 56m 15s</ElapsedTime>
    <FailedTests>7</FailedTests>
    <SkippedTests>7</SkippedTests>
    <PassedTests>280</PassedTests>
    <MDResultFile>c:\pnpbuildtemp\PnPUnitTestResults-20160301-OnlineCred-635924727446995321.md</MDResultFile>
  </PnPTestSummary>
  <PnPTestSummary>
    <PnPConfigurationToTest>OnPremAppOnly</PnPConfigurationToTest>
    <TestDate>Tuesday, March 1, 2016</TestDate>
    <TestTime>10:24 PM</TestTime>
    <PnPBranch>dev</PnPBranch>
    <VSBuildConfiguration>debug15</VSBuildConfiguration>
    <NumberOfTests>286</NumberOfTests>
    <ElapsedTime>0h 21m 18s</ElapsedTime>
    <FailedTests>0</FailedTests>
    <SkippedTests>51</SkippedTests>
    <PassedTests>235</PassedTests>
    <MDResultFile>c:\pnpbuildtemp\PnPUnitTestResults-20160301-OnPremAppOnly-635924714410499956.md</MDResultFile>
  </PnPTestSummary>
  <PnPTestSummary>
    <PnPConfigurationToTest>OnPremCred</PnPConfigurationToTest>
    <TestDate>Tuesday, March 1, 2016</TestDate>
    <TestTime>10:00 PM</TestTime>
    <PnPBranch>dev</PnPBranch>
    <VSBuildConfiguration>debug15</VSBuildConfiguration>
    <NumberOfTests>286</NumberOfTests>
    <ElapsedTime>0h 23m 9s</ElapsedTime>
    <FailedTests>0</FailedTests>
    <SkippedTests>21</SkippedTests>
    <PassedTests>265</PassedTests>
    <MDResultFile>c:\pnpbuildtemp\PnPUnitTestResults-20160301-OnPremCred-635924700260833129.md</MDResultFile>
  </PnPTestSummary>
  <PnPTestSummary>
    <PnPConfigurationToTest>OnlineAppOnly</PnPConfigurationToTest>
    <TestDate>Tuesday, March 1, 2016</TestDate>
    <TestTime>11:31 PM</TestTime>
    <PnPBranch>dev</PnPBranch>
    <VSBuildConfiguration>debug</VSBuildConfiguration>
    <NumberOfTests>294</NumberOfTests>
    <ElapsedTime>0h 55m 32s</ElapsedTime>
    <FailedTests>5</FailedTests>
    <SkippedTests>39</SkippedTests>
    <PassedTests>250</PassedTests>
    <MDResultFile>c:\pnpbuildtemp\PnPUnitTestResults-20160301-OnlineAppOnly-635923891104326573.md</MDResultFile>
  </PnPTestSummary>
  <PnPTestSummary>
    <PnPConfigurationToTest>OnlineCred</PnPConfigurationToTest>
    <TestDate>Monday, February 29, 2016</TestDate>
    <TestTime>10:45 PM</TestTime>
    <PnPBranch>dev</PnPBranch>
    <VSBuildConfiguration>debug</VSBuildConfiguration>
    <NumberOfTests>294</NumberOfTests>
    <ElapsedTime>0h 46m 17s</ElapsedTime>
    <FailedTests>3</FailedTests>
    <SkippedTests>7</SkippedTests>
    <PassedTests>284</PassedTests>
    <MDResultFile>c:\pnpbuildtemp\PnPUnitTestResults-20160229-OnlineCred-635923863065680366.md</MDResultFile>
  </PnPTestSummary>
  <PnPTestSummary>
    <PnPConfigurationToTest>OnPremAppOnly</PnPConfigurationToTest>
    <TestDate>Monday, February 29, 2016</TestDate>
    <TestTime>10:23 PM</TestTime>
    <PnPBranch>dev</PnPBranch>
    <VSBuildConfiguration>debug15</VSBuildConfiguration>
    <NumberOfTests>286</NumberOfTests>
    <ElapsedTime>0h 21m 11s</ElapsedTime>
    <FailedTests>0</FailedTests>
    <SkippedTests>51</SkippedTests>
    <PassedTests>235</PassedTests>
    <MDResultFile>c:\pnpbuildtemp\PnPUnitTestResults-20160229-OnPremAppOnly-635923850094780251.md</MDResultFile>
  </PnPTestSummary>
  <PnPTestSummary>
    <PnPConfigurationToTest>OnPremCred</PnPConfigurationToTest>
    <TestDate>Monday, February 29, 2016</TestDate>
    <TestTime>10:00 PM</TestTime>
    <PnPBranch>dev</PnPBranch>
    <VSBuildConfiguration>debug15</VSBuildConfiguration>
    <NumberOfTests>286</NumberOfTests>
    <ElapsedTime>0h 22m 39s</ElapsedTime>
    <FailedTests>0</FailedTests>
    <SkippedTests>21</SkippedTests>
    <PassedTests>265</PassedTests>
    <MDResultFile>c:\pnpbuildtemp\PnPUnitTestResults-20160229-OnPremCred-635923836254560416.md</MDResultFile>
  </PnPTestSummary>
  <PnPTestSummary>
    <PnPConfigurationToTest>OnlineAppOnly</PnPConfigurationToTest>
    <TestDate>Monday, February 29, 2016</TestDate>
    <TestTime>11:39 PM</TestTime>
    <PnPBranch>dev</PnPBranch>
    <VSBuildConfiguration>debug</VSBuildConfiguration>
    <NumberOfTests>294</NumberOfTests>
    <ElapsedTime>1h 1m 0s</ElapsedTime>
    <FailedTests>11</FailedTests>
    <SkippedTests>39</SkippedTests>
    <PassedTests>244</PassedTests>
    <MDResultFile>c:\pnpbuildtemp\PnPUnitTestResults-20160229-OnlineAppOnly-635923031441872259.md</MDResultFile>
  </PnPTestSummary>
  <PnPTestSummary>
    <PnPConfigurationToTest>OnlineCred</PnPConfigurationToTest>
    <TestDate>Sunday, February 28, 2016</TestDate>
    <TestTime>10:45 PM</TestTime>
    <PnPBranch>dev</PnPBranch>
    <VSBuildConfiguration>debug</VSBuildConfiguration>
    <NumberOfTests>294</NumberOfTests>
    <ElapsedTime>0h 52m 43s</ElapsedTime>
    <FailedTests>10</FailedTests>
    <SkippedTests>7</SkippedTests>
    <PassedTests>277</PassedTests>
    <MDResultFile>c:\pnpbuildtemp\PnPUnitTestResults-20160228-OnlineCred-635922999559309119.md</MDResultFile>
  </PnPTestSummary>
  <PnPTestSummary>
    <PnPConfigurationToTest>OnPremAppOnly</PnPConfigurationToTest>
    <TestDate>Sunday, February 28, 2016</TestDate>
    <TestTime>10:24 PM</TestTime>
    <PnPBranch>dev</PnPBranch>
    <VSBuildConfiguration>debug15</VSBuildConfiguration>
    <NumberOfTests>286</NumberOfTests>
    <ElapsedTime>0h 21m 22s</ElapsedTime>
    <FailedTests>0</FailedTests>
    <SkippedTests>51</SkippedTests>
    <PassedTests>235</PassedTests>
    <MDResultFile>c:\pnpbuildtemp\PnPUnitTestResults-20160228-OnPremAppOnly-635922986477564277.md</MDResultFile>
  </PnPTestSummary>
  <PnPTestSummary>
    <PnPConfigurationToTest>OnPremCred</PnPConfigurationToTest>
    <TestDate>Sunday, February 28, 2016</TestDate>
    <TestTime>10:00 PM</TestTime>
    <PnPBranch>dev</PnPBranch>
    <VSBuildConfiguration>debug15</VSBuildConfiguration>
    <NumberOfTests>286</NumberOfTests>
    <ElapsedTime>0h 23m 16s</ElapsedTime>
    <FailedTests>0</FailedTests>
    <SkippedTests>21</SkippedTests>
    <PassedTests>265</PassedTests>
    <MDResultFile>c:\pnpbuildtemp\PnPUnitTestResults-20160228-OnPremCred-635922972263370538.md</MDResultFile>
  </PnPTestSummary>
  <PnPTestSummary>
    <PnPConfigurationToTest>OnlineAppOnly</PnPConfigurationToTest>
    <TestDate>Sunday, February 28, 2016</TestDate>
    <TestTime>11:36 PM</TestTime>
    <PnPBranch>dev</PnPBranch>
    <VSBuildConfiguration>debug</VSBuildConfiguration>
    <NumberOfTests>294</NumberOfTests>
    <ElapsedTime>1h 0m 5s</ElapsedTime>
    <FailedTests>12</FailedTests>
    <SkippedTests>39</SkippedTests>
    <PassedTests>243</PassedTests>
    <MDResultFile>c:\pnpbuildtemp\PnPUnitTestResults-20160228-OnlineAppOnly-635922166150386989.md</MDResultFile>
  </PnPTestSummary>
  <PnPTestSummary>
    <PnPConfigurationToTest>OnlineCred</PnPConfigurationToTest>
    <TestDate>Saturday, February 27, 2016</TestDate>
    <TestTime>10:49 PM</TestTime>
    <PnPBranch>dev</PnPBranch>
    <VSBuildConfiguration>debug</VSBuildConfiguration>
    <NumberOfTests>294</NumberOfTests>
    <ElapsedTime>0h 46m 34s</ElapsedTime>
    <FailedTests>12</FailedTests>
    <SkippedTests>7</SkippedTests>
    <PassedTests>275</PassedTests>
    <MDResultFile>c:\pnpbuildtemp\PnPUnitTestResults-20160227-OnlineCred-635922137847400540.md</MDResultFile>
  </PnPTestSummary>
  <PnPTestSummary>
    <PnPConfigurationToTest>OnPremAppOnly</PnPConfigurationToTest>
    <TestDate>Saturday, February 27, 2016</TestDate>
    <TestTime>10:23 PM</TestTime>
    <PnPBranch>dev</PnPBranch>
    <VSBuildConfiguration>debug15</VSBuildConfiguration>
    <NumberOfTests>286</NumberOfTests>
    <ElapsedTime>0h 25m 22s</ElapsedTime>
    <FailedTests>0</FailedTests>
    <SkippedTests>51</SkippedTests>
    <PassedTests>235</PassedTests>
    <MDResultFile>c:\pnpbuildtemp\PnPUnitTestResults-20160227-OnPremAppOnly-635922122273754382.md</MDResultFile>
  </PnPTestSummary>
  <PnPTestSummary>
    <PnPConfigurationToTest>OnPremCred</PnPConfigurationToTest>
    <TestDate>Saturday, February 27, 2016</TestDate>
    <TestTime>10:00 PM</TestTime>
    <PnPBranch>dev</PnPBranch>
    <VSBuildConfiguration>debug15</VSBuildConfiguration>
    <NumberOfTests>286</NumberOfTests>
    <ElapsedTime>0h 22m 55s</ElapsedTime>
    <FailedTests>0</FailedTests>
    <SkippedTests>21</SkippedTests>
    <PassedTests>265</PassedTests>
    <MDResultFile>c:\pnpbuildtemp\PnPUnitTestResults-20160227-OnPremCred-635922108276578167.md</MDResultFile>
  </PnPTestSummary>
  <PnPTestSummary>
    <PnPConfigurationToTest>OnlineAppOnly</PnPConfigurationToTest>
    <TestDate>Friday, February 26, 2016</TestDate>
    <TestTime>11:18 PM</TestTime>
    <PnPBranch>dev</PnPBranch>
    <VSBuildConfiguration>debug</VSBuildConfiguration>
    <NumberOfTests>294</NumberOfTests>
    <ElapsedTime>0h 1m 7s</ElapsedTime>
    <FailedTests>176</FailedTests>
    <SkippedTests>36</SkippedTests>
    <PassedTests>82</PassedTests>
    <MDResultFile>c:\pnpbuildtemp\PnPUnitTestResults-20160226-OnlineAppOnly-635920426805279839.md</MDResultFile>
  </PnPTestSummary>
  <PnPTestSummary>
    <PnPConfigurationToTest>OnlineCred</PnPConfigurationToTest>
    <TestDate>Thursday, February 25, 2016</TestDate>
    <TestTime>10:25 PM</TestTime>
    <PnPBranch>dev</PnPBranch>
    <VSBuildConfiguration>debug</VSBuildConfiguration>
    <NumberOfTests>294</NumberOfTests>
    <ElapsedTime>0h 52m 25s</ElapsedTime>
    <FailedTests>11</FailedTests>
    <SkippedTests>7</SkippedTests>
    <PassedTests>276</PassedTests>
    <MDResultFile>c:\pnpbuildtemp\PnPUnitTestResults-20160225-OnlineCred-635920395096508100.md</MDResultFile>
  </PnPTestSummary>
  <PnPTestSummary>
    <PnPConfigurationToTest>OnPremAppOnly</PnPConfigurationToTest>
    <TestDate>Thursday, February 25, 2016</TestDate>
    <TestTime>10:23 PM</TestTime>
    <PnPBranch>dev</PnPBranch>
    <VSBuildConfiguration>debug15</VSBuildConfiguration>
    <NumberOfTests>286</NumberOfTests>
    <ElapsedTime>0h 0m 56s</ElapsedTime>
    <FailedTests>168</FailedTests>
    <SkippedTests>50</SkippedTests>
    <PassedTests>68</PassedTests>
    <MDResultFile>c:\pnpbuildtemp\PnPUnitTestResults-20160225-OnPremAppOnly-635920394290863765.md</MDResultFile>
  </PnPTestSummary>
  <PnPTestSummary>
    <PnPConfigurationToTest>OnPremCred</PnPConfigurationToTest>
    <TestDate>Thursday, February 25, 2016</TestDate>
    <TestTime>10:00 PM</TestTime>
    <PnPBranch>dev</PnPBranch>
    <VSBuildConfiguration>debug15</VSBuildConfiguration>
    <NumberOfTests>286</NumberOfTests>
    <ElapsedTime>0h 22m 57s</ElapsedTime>
    <FailedTests>0</FailedTests>
    <SkippedTests>21</SkippedTests>
    <PassedTests>265</PassedTests>
    <MDResultFile>c:\pnpbuildtemp\PnPUnitTestResults-20160225-OnPremCred-635920380276501120.md</MDResultFile>
  </PnPTestSummary>
  <PnPTestSummary>
    <PnPConfigurationToTest>OnlineAppOnly</PnPConfigurationToTest>
    <TestDate>Thursday, February 25, 2016</TestDate>
    <TestTime>11:21 PM</TestTime>
    <PnPBranch>dev</PnPBranch>
    <VSBuildConfiguration>debug</VSBuildConfiguration>
    <NumberOfTests>294</NumberOfTests>
    <ElapsedTime>0h 1m 7s</ElapsedTime>
    <FailedTests>176</FailedTests>
    <SkippedTests>36</SkippedTests>
    <PassedTests>82</PassedTests>
    <MDResultFile>c:\pnpbuildtemp\PnPUnitTestResults-20160225-OnlineAppOnly-635919565056775523.md</MDResultFile>
  </PnPTestSummary>
  <PnPTestSummary>
    <PnPConfigurationToTest>OnlineCred</PnPConfigurationToTest>
    <TestDate>Wednesday, February 24, 2016</TestDate>
    <TestTime>10:24 PM</TestTime>
    <PnPBranch>dev</PnPBranch>
    <VSBuildConfiguration>debug</VSBuildConfiguration>
    <NumberOfTests>294</NumberOfTests>
    <ElapsedTime>0h 56m 25s</ElapsedTime>
    <FailedTests>10</FailedTests>
    <SkippedTests>7</SkippedTests>
    <PassedTests>277</PassedTests>
    <MDResultFile>c:\pnpbuildtemp\PnPUnitTestResults-20160224-OnlineCred-635919530947137976.md</MDResultFile>
  </PnPTestSummary>
  <PnPTestSummary>
    <PnPConfigurationToTest>OnPremAppOnly</PnPConfigurationToTest>
    <TestDate>Wednesday, February 24, 2016</TestDate>
    <TestTime>10:23 PM</TestTime>
    <PnPBranch>dev</PnPBranch>
    <VSBuildConfiguration>debug15</VSBuildConfiguration>
    <NumberOfTests>286</NumberOfTests>
    <ElapsedTime>0h 0m 54s</ElapsedTime>
    <FailedTests>168</FailedTests>
    <SkippedTests>50</SkippedTests>
    <PassedTests>68</PassedTests>
    <MDResultFile>c:\pnpbuildtemp\PnPUnitTestResults-20160224-OnPremAppOnly-635919530148833495.md</MDResultFile>
  </PnPTestSummary>
  <PnPTestSummary>
    <PnPConfigurationToTest>OnPremCred</PnPConfigurationToTest>
    <TestDate>Wednesday, February 24, 2016</TestDate>
    <TestTime>10:00 PM</TestTime>
    <PnPBranch>dev</PnPBranch>
    <VSBuildConfiguration>debug15</VSBuildConfiguration>
    <NumberOfTests>286</NumberOfTests>
    <ElapsedTime>0h 22m 44s</ElapsedTime>
    <FailedTests>0</FailedTests>
    <SkippedTests>21</SkippedTests>
    <PassedTests>265</PassedTests>
    <MDResultFile>c:\pnpbuildtemp\PnPUnitTestResults-20160224-OnPremCred-635919516259095878.md</MDResultFile>
  </PnPTestSummary>
  <PnPTestSummary>
    <PnPConfigurationToTest>OnlineAppOnly</PnPConfigurationToTest>
    <TestDate>Wednesday, February 24, 2016</TestDate>
    <TestTime>11:33 PM</TestTime>
    <PnPBranch>dev</PnPBranch>
    <VSBuildConfiguration>debug</VSBuildConfiguration>
    <NumberOfTests>294</NumberOfTests>
    <ElapsedTime>0h 1m 6s</ElapsedTime>
    <FailedTests>176</FailedTests>
    <SkippedTests>36</SkippedTests>
    <PassedTests>82</PassedTests>
    <MDResultFile>c:\pnpbuildtemp\PnPUnitTestResults-20160224-OnlineAppOnly-635918708021879466.md</MDResultFile>
  </PnPTestSummary>
  <PnPTestSummary>
    <PnPConfigurationToTest>OnlineCred</PnPConfigurationToTest>
    <TestDate>Tuesday, February 23, 2016</TestDate>
    <TestTime>10:25 PM</TestTime>
    <PnPBranch>dev</PnPBranch>
    <VSBuildConfiguration>debug</VSBuildConfiguration>
    <NumberOfTests>294</NumberOfTests>
    <ElapsedTime>1h 7m 32s</ElapsedTime>
    <FailedTests>11</FailedTests>
    <SkippedTests>7</SkippedTests>
    <PassedTests>276</PassedTests>
    <MDResultFile>c:\pnpbuildtemp\PnPUnitTestResults-20160223-OnlineCred-635918667228821154.md</MDResultFile>
  </PnPTestSummary>
  <PnPTestSummary>
    <PnPConfigurationToTest>OnPremAppOnly</PnPConfigurationToTest>
    <TestDate>Tuesday, February 23, 2016</TestDate>
    <TestTime>10:24 PM</TestTime>
    <PnPBranch>dev</PnPBranch>
    <VSBuildConfiguration>debug15</VSBuildConfiguration>
    <NumberOfTests>286</NumberOfTests>
    <ElapsedTime>0h 0m 57s</ElapsedTime>
    <FailedTests>168</FailedTests>
    <SkippedTests>50</SkippedTests>
    <PassedTests>68</PassedTests>
    <MDResultFile>c:\pnpbuildtemp\PnPUnitTestResults-20160223-OnPremAppOnly-635918666404989853.md</MDResultFile>
  </PnPTestSummary>
  <PnPTestSummary>
    <PnPConfigurationToTest>OnPremCred</PnPConfigurationToTest>
    <TestDate>Tuesday, February 23, 2016</TestDate>
    <TestTime>10:00 PM</TestTime>
    <PnPBranch>dev</PnPBranch>
    <VSBuildConfiguration>debug15</VSBuildConfiguration>
    <NumberOfTests>286</NumberOfTests>
    <ElapsedTime>0h 23m 9s</ElapsedTime>
    <FailedTests>0</FailedTests>
    <SkippedTests>21</SkippedTests>
    <PassedTests>265</PassedTests>
    <MDResultFile>c:\pnpbuildtemp\PnPUnitTestResults-20160223-OnPremCred-635918652243710637.md</MDResultFile>
  </PnPTestSummary>
  <PnPTestSummary>
    <PnPConfigurationToTest>OnlineAppOnly</PnPConfigurationToTest>
    <TestDate>Monday, February 22, 2016</TestDate>
    <TestTime>11:28 PM</TestTime>
    <PnPBranch>dev</PnPBranch>
    <VSBuildConfiguration>debug</VSBuildConfiguration>
    <NumberOfTests>294</NumberOfTests>
    <ElapsedTime>0h 38m 29s</ElapsedTime>
    <FailedTests>16</FailedTests>
    <SkippedTests>37</SkippedTests>
    <PassedTests>241</PassedTests>
    <MDResultFile>c:\pnpbuildtemp\PnPUnitTestResults-20160222-OnlineAppOnly-635916976923732089.md</MDResultFile>
  </PnPTestSummary>
  <PnPTestSummary>
    <PnPConfigurationToTest>OnlineCred</PnPConfigurationToTest>
    <TestDate>Sunday, February 21, 2016</TestDate>
    <TestTime>10:45 PM</TestTime>
    <PnPBranch>dev</PnPBranch>
    <VSBuildConfiguration>debug</VSBuildConfiguration>
    <NumberOfTests>294</NumberOfTests>
    <ElapsedTime>0h 42m 53s</ElapsedTime>
    <FailedTests>16</FailedTests>
    <SkippedTests>7</SkippedTests>
    <PassedTests>271</PassedTests>
    <MDResultFile>c:\pnpbuildtemp\PnPUnitTestResults-20160221-OnlineCred-635916951012143900.md</MDResultFile>
  </PnPTestSummary>
  <PnPTestSummary>
    <PnPConfigurationToTest>OnPremAppOnly</PnPConfigurationToTest>
    <TestDate>Sunday, February 21, 2016</TestDate>
    <TestTime>10:23 PM</TestTime>
    <PnPBranch>dev</PnPBranch>
    <VSBuildConfiguration>debug15</VSBuildConfiguration>
    <NumberOfTests>286</NumberOfTests>
    <ElapsedTime>0h 21m 7s</ElapsedTime>
    <FailedTests>0</FailedTests>
    <SkippedTests>51</SkippedTests>
    <PassedTests>235</PassedTests>
    <MDResultFile>c:\pnpbuildtemp\PnPUnitTestResults-20160221-OnPremAppOnly-635916938159121242.md</MDResultFile>
  </PnPTestSummary>
  <PnPTestSummary>
    <PnPConfigurationToTest>OnPremCred</PnPConfigurationToTest>
    <TestDate>Sunday, February 21, 2016</TestDate>
    <TestTime>10:00 PM</TestTime>
    <PnPBranch>dev</PnPBranch>
    <VSBuildConfiguration>debug15</VSBuildConfiguration>
    <NumberOfTests>286</NumberOfTests>
    <ElapsedTime>0h 22m 58s</ElapsedTime>
    <FailedTests>0</FailedTests>
    <SkippedTests>21</SkippedTests>
    <PassedTests>265</PassedTests>
    <MDResultFile>c:\pnpbuildtemp\PnPUnitTestResults-20160221-OnPremCred-635916924195335938.md</MDResultFile>
  </PnPTestSummary>
  <PnPTestSummary>
    <PnPConfigurationToTest>OnlineAppOnly</PnPConfigurationToTest>
    <TestDate>Sunday, February 21, 2016</TestDate>
    <TestTime>12:04 AM</TestTime>
    <PnPBranch>dev</PnPBranch>
    <VSBuildConfiguration>debug</VSBuildConfiguration>
    <NumberOfTests>294</NumberOfTests>
    <ElapsedTime>0h 45m 7s</ElapsedTime>
    <FailedTests>4</FailedTests>
    <SkippedTests>38</SkippedTests>
    <PassedTests>252</PassedTests>
    <MDResultFile>c:\pnpbuildtemp\PnPUnitTestResults-20160221-OnlineAppOnly-635916134560050806.md</MDResultFile>
  </PnPTestSummary>
  <PnPTestSummary>
    <PnPConfigurationToTest>OnlineCred</PnPConfigurationToTest>
    <TestDate>Saturday, February 20, 2016</TestDate>
    <TestTime>10:49 PM</TestTime>
    <PnPBranch>dev</PnPBranch>
    <VSBuildConfiguration>debug</VSBuildConfiguration>
    <NumberOfTests>294</NumberOfTests>
    <ElapsedTime>1h 14m 24s</ElapsedTime>
    <FailedTests>3</FailedTests>
    <SkippedTests>7</SkippedTests>
    <PassedTests>284</PassedTests>
    <MDResultFile>c:\pnpbuildtemp\PnPUnitTestResults-20160220-OnlineCred-635916089631837831.md</MDResultFile>
  </PnPTestSummary>
  <PnPTestSummary>
    <PnPConfigurationToTest>OnPremAppOnly</PnPConfigurationToTest>
    <TestDate>Saturday, February 20, 2016</TestDate>
    <TestTime>10:23 PM</TestTime>
    <PnPBranch>dev</PnPBranch>
    <VSBuildConfiguration>debug15</VSBuildConfiguration>
    <NumberOfTests>286</NumberOfTests>
    <ElapsedTime>0h 25m 23s</ElapsedTime>
    <FailedTests>0</FailedTests>
    <SkippedTests>51</SkippedTests>
    <PassedTests>235</PassedTests>
    <MDResultFile>c:\pnpbuildtemp\PnPUnitTestResults-20160220-OnPremAppOnly-635916074140299151.md</MDResultFile>
  </PnPTestSummary>
  <PnPTestSummary>
    <PnPConfigurationToTest>OnPremCred</PnPConfigurationToTest>
    <TestDate>Saturday, February 20, 2016</TestDate>
    <TestTime>10:00 PM</TestTime>
    <PnPBranch>dev</PnPBranch>
    <VSBuildConfiguration>debug15</VSBuildConfiguration>
    <NumberOfTests>286</NumberOfTests>
    <ElapsedTime>0h 22m 56s</ElapsedTime>
    <FailedTests>0</FailedTests>
    <SkippedTests>21</SkippedTests>
    <PassedTests>265</PassedTests>
    <MDResultFile>c:\pnpbuildtemp\PnPUnitTestResults-20160220-OnPremCred-635916060191683043.md</MDResultFile>
  </PnPTestSummary>
  <PnPTestSummary>
    <PnPConfigurationToTest>OnlineAppOnly</PnPConfigurationToTest>
    <TestDate>Saturday, February 20, 2016</TestDate>
    <TestTime>11:37 PM</TestTime>
    <PnPBranch>dev</PnPBranch>
    <VSBuildConfiguration>debug</VSBuildConfiguration>
    <NumberOfTests>294</NumberOfTests>
    <ElapsedTime>0h 47m 22s</ElapsedTime>
    <FailedTests>2</FailedTests>
    <SkippedTests>39</SkippedTests>
    <PassedTests>253</PassedTests>
    <MDResultFile>c:\pnpbuildtemp\PnPUnitTestResults-20160220-OnlineAppOnly-635915254373124698.md</MDResultFile>
  </PnPTestSummary>
  <PnPTestSummary>
    <PnPConfigurationToTest>OnlineCred</PnPConfigurationToTest>
    <TestDate>Friday, February 19, 2016</TestDate>
    <TestTime>10:45 PM</TestTime>
    <PnPBranch>dev</PnPBranch>
    <VSBuildConfiguration>debug</VSBuildConfiguration>
    <NumberOfTests>294</NumberOfTests>
    <ElapsedTime>0h 51m 53s</ElapsedTime>
    <FailedTests>5</FailedTests>
    <SkippedTests>7</SkippedTests>
    <PassedTests>282</PassedTests>
    <MDResultFile>c:\pnpbuildtemp\PnPUnitTestResults-20160219-OnlineCred-635915223061065663.md</MDResultFile>
  </PnPTestSummary>
  <PnPTestSummary>
    <PnPConfigurationToTest>OnPremAppOnly</PnPConfigurationToTest>
    <TestDate>Friday, February 19, 2016</TestDate>
    <TestTime>10:23 PM</TestTime>
    <PnPBranch>dev</PnPBranch>
    <VSBuildConfiguration>debug15</VSBuildConfiguration>
    <NumberOfTests>286</NumberOfTests>
    <ElapsedTime>0h 21m 2s</ElapsedTime>
    <FailedTests>0</FailedTests>
    <SkippedTests>51</SkippedTests>
    <PassedTests>235</PassedTests>
    <MDResultFile>c:\pnpbuildtemp\PnPUnitTestResults-20160219-OnPremAppOnly-635915210261360939.md</MDResultFile>
  </PnPTestSummary>
  <PnPTestSummary>
    <PnPConfigurationToTest>OnPremCred</PnPConfigurationToTest>
    <TestDate>Friday, February 19, 2016</TestDate>
    <TestTime>10:00 PM</TestTime>
    <PnPBranch>dev</PnPBranch>
    <VSBuildConfiguration>debug15</VSBuildConfiguration>
    <NumberOfTests>286</NumberOfTests>
    <ElapsedTime>0h 23m 3s</ElapsedTime>
    <FailedTests>0</FailedTests>
    <SkippedTests>21</SkippedTests>
    <PassedTests>265</PassedTests>
    <MDResultFile>c:\pnpbuildtemp\PnPUnitTestResults-20160219-OnPremCred-635915196254473155.md</MDResultFile>
  </PnPTestSummary>
  <PnPTestSummary>
    <PnPConfigurationToTest>OnlineAppOnly</PnPConfigurationToTest>
    <TestDate>Friday, February 19, 2016</TestDate>
    <TestTime>11:35 PM</TestTime>
    <PnPBranch>dev</PnPBranch>
    <VSBuildConfiguration>debug</VSBuildConfiguration>
    <NumberOfTests>294</NumberOfTests>
    <ElapsedTime>0h 32m 29s</ElapsedTime>
    <FailedTests>144</FailedTests>
    <SkippedTests>36</SkippedTests>
    <PassedTests>114</PassedTests>
    <MDResultFile>c:\pnpbuildtemp\PnPUnitTestResults-20160219-OnlineAppOnly-635914389084387695.md</MDResultFile>
  </PnPTestSummary>
  <PnPTestSummary>
    <PnPConfigurationToTest>OnlineCred</PnPConfigurationToTest>
    <TestDate>Thursday, February 18, 2016</TestDate>
    <TestTime>10:45 PM</TestTime>
    <PnPBranch>dev</PnPBranch>
    <VSBuildConfiguration>debug</VSBuildConfiguration>
    <NumberOfTests>294</NumberOfTests>
    <ElapsedTime>0h 49m 37s</ElapsedTime>
    <FailedTests>1</FailedTests>
    <SkippedTests>7</SkippedTests>
    <PassedTests>286</PassedTests>
    <MDResultFile>c:\pnpbuildtemp\PnPUnitTestResults-20160218-OnlineCred-635914359126069678.md</MDResultFile>
  </PnPTestSummary>
  <PnPTestSummary>
    <PnPConfigurationToTest>OnPremAppOnly</PnPConfigurationToTest>
    <TestDate>Thursday, February 18, 2016</TestDate>
    <TestTime>10:23 PM</TestTime>
    <PnPBranch>dev</PnPBranch>
    <VSBuildConfiguration>debug15</VSBuildConfiguration>
    <NumberOfTests>286</NumberOfTests>
    <ElapsedTime>0h 21m 9s</ElapsedTime>
    <FailedTests>0</FailedTests>
    <SkippedTests>51</SkippedTests>
    <PassedTests>235</PassedTests>
    <MDResultFile>c:\pnpbuildtemp\PnPUnitTestResults-20160218-OnPremAppOnly-635914346234356039.md</MDResultFile>
  </PnPTestSummary>
  <PnPTestSummary>
    <PnPConfigurationToTest>OnPremCred</PnPConfigurationToTest>
    <TestDate>Thursday, February 18, 2016</TestDate>
    <TestTime>10:00 PM</TestTime>
    <PnPBranch>dev</PnPBranch>
    <VSBuildConfiguration>debug15</VSBuildConfiguration>
    <NumberOfTests>286</NumberOfTests>
    <ElapsedTime>0h 23m 1s</ElapsedTime>
    <FailedTests>0</FailedTests>
    <SkippedTests>21</SkippedTests>
    <PassedTests>265</PassedTests>
    <MDResultFile>c:\pnpbuildtemp\PnPUnitTestResults-20160218-OnPremCred-635914332246633638.md</MDResultFile>
  </PnPTestSummary>
  <PnPTestSummary>
    <PnPConfigurationToTest>OnlineAppOnly</PnPConfigurationToTest>
    <TestDate>Thursday, February 18, 2016</TestDate>
    <TestTime>11:35 PM</TestTime>
    <PnPBranch>dev</PnPBranch>
    <VSBuildConfiguration>debug</VSBuildConfiguration>
    <NumberOfTests>294</NumberOfTests>
    <ElapsedTime>0h 44m 48s</ElapsedTime>
    <FailedTests>1</FailedTests>
    <SkippedTests>39</SkippedTests>
    <PassedTests>254</PassedTests>
    <MDResultFile>c:\pnpbuildtemp\PnPUnitTestResults-20160218-OnlineAppOnly-635913525248669880.md</MDResultFile>
  </PnPTestSummary>
  <PnPTestSummary>
    <PnPConfigurationToTest>OnlineCred</PnPConfigurationToTest>
    <TestDate>Wednesday, February 17, 2016</TestDate>
    <TestTime>10:44 PM</TestTime>
    <PnPBranch>dev</PnPBranch>
    <VSBuildConfiguration>debug</VSBuildConfiguration>
    <NumberOfTests>294</NumberOfTests>
    <ElapsedTime>0h 50m 35s</ElapsedTime>
    <FailedTests>1</FailedTests>
    <SkippedTests>7</SkippedTests>
    <PassedTests>286</PassedTests>
    <MDResultFile>c:\pnpbuildtemp\PnPUnitTestResults-20160217-OnlineCred-635913494710655934.md</MDResultFile>
  </PnPTestSummary>
  <PnPTestSummary>
    <PnPConfigurationToTest>OnPremAppOnly</PnPConfigurationToTest>
    <TestDate>Wednesday, February 17, 2016</TestDate>
    <TestTime>10:23 PM</TestTime>
    <PnPBranch>dev</PnPBranch>
    <VSBuildConfiguration>debug15</VSBuildConfiguration>
    <NumberOfTests>286</NumberOfTests>
    <ElapsedTime>0h 20m 54s</ElapsedTime>
    <FailedTests>0</FailedTests>
    <SkippedTests>51</SkippedTests>
    <PassedTests>235</PassedTests>
    <MDResultFile>c:\pnpbuildtemp\PnPUnitTestResults-20160217-OnPremAppOnly-635913481978834145.md</MDResultFile>
  </PnPTestSummary>
  <PnPTestSummary>
    <PnPConfigurationToTest>OnPremCred</PnPConfigurationToTest>
    <TestDate>Wednesday, February 17, 2016</TestDate>
    <TestTime>10:00 PM</TestTime>
    <PnPBranch>dev</PnPBranch>
    <VSBuildConfiguration>debug15</VSBuildConfiguration>
    <NumberOfTests>286</NumberOfTests>
    <ElapsedTime>0h 22m 34s</ElapsedTime>
    <FailedTests>0</FailedTests>
    <SkippedTests>21</SkippedTests>
    <PassedTests>265</PassedTests>
    <MDResultFile>c:\pnpbuildtemp\PnPUnitTestResults-20160217-OnPremCred-635913468259384701.md</MDResultFile>
  </PnPTestSummary>
  <PnPTestSummary>
    <PnPConfigurationToTest>OnlineAppOnly</PnPConfigurationToTest>
    <TestDate>Wednesday, February 17, 2016</TestDate>
    <TestTime>11:43 PM</TestTime>
    <PnPBranch>dev</PnPBranch>
    <VSBuildConfiguration>debug</VSBuildConfiguration>
    <NumberOfTests>294</NumberOfTests>
    <ElapsedTime>0h 51m 26s</ElapsedTime>
    <FailedTests>1</FailedTests>
    <SkippedTests>39</SkippedTests>
    <PassedTests>254</PassedTests>
    <MDResultFile>c:\pnpbuildtemp\PnPUnitTestResults-20160217-OnlineAppOnly-635912665978686585.md</MDResultFile>
  </PnPTestSummary>
  <PnPTestSummary>
    <PnPConfigurationToTest>OnlineCred</PnPConfigurationToTest>
    <TestDate>Tuesday, February 16, 2016</TestDate>
    <TestTime>10:44 PM</TestTime>
    <PnPBranch>dev</PnPBranch>
    <VSBuildConfiguration>debug</VSBuildConfiguration>
    <NumberOfTests>294</NumberOfTests>
    <ElapsedTime>0h 58m 31s</ElapsedTime>
    <FailedTests>2</FailedTests>
    <SkippedTests>7</SkippedTests>
    <PassedTests>285</PassedTests>
    <MDResultFile>c:\pnpbuildtemp\PnPUnitTestResults-20160216-OnlineCred-635912630686264993.md</MDResultFile>
  </PnPTestSummary>
  <PnPTestSummary>
    <PnPConfigurationToTest>OnPremAppOnly</PnPConfigurationToTest>
    <TestDate>Tuesday, February 16, 2016</TestDate>
    <TestTime>10:23 PM</TestTime>
    <PnPBranch>dev</PnPBranch>
    <VSBuildConfiguration>debug15</VSBuildConfiguration>
    <NumberOfTests>286</NumberOfTests>
    <ElapsedTime>0h 20m 44s</ElapsedTime>
    <FailedTests>0</FailedTests>
    <SkippedTests>51</SkippedTests>
    <PassedTests>235</PassedTests>
    <MDResultFile>c:\pnpbuildtemp\PnPUnitTestResults-20160216-OnPremAppOnly-635912618059405868.md</MDResultFile>
  </PnPTestSummary>
  <PnPTestSummary>
    <PnPConfigurationToTest>OnPremCred</PnPConfigurationToTest>
    <TestDate>Tuesday, February 16, 2016</TestDate>
    <TestTime>10:00 PM</TestTime>
    <PnPBranch>dev</PnPBranch>
    <VSBuildConfiguration>debug15</VSBuildConfiguration>
    <NumberOfTests>286</NumberOfTests>
    <ElapsedTime>0h 22m 34s</ElapsedTime>
    <FailedTests>0</FailedTests>
    <SkippedTests>21</SkippedTests>
    <PassedTests>265</PassedTests>
    <MDResultFile>c:\pnpbuildtemp\PnPUnitTestResults-20160216-OnPremCred-635912604324002255.md</MDResultFile>
  </PnPTestSummary>
  <PnPTestSummary>
    <PnPConfigurationToTest>OnlineAppOnly</PnPConfigurationToTest>
    <TestDate>Tuesday, February 16, 2016</TestDate>
    <TestTime>11:41 PM</TestTime>
    <PnPBranch>dev</PnPBranch>
    <VSBuildConfiguration>debug</VSBuildConfiguration>
    <NumberOfTests>294</NumberOfTests>
    <ElapsedTime>0h 58m 15s</ElapsedTime>
    <FailedTests>0</FailedTests>
    <SkippedTests>39</SkippedTests>
    <PassedTests>255</PassedTests>
    <MDResultFile>c:\pnpbuildtemp\PnPUnitTestResults-20160216-OnlineAppOnly-635911800839156527.md</MDResultFile>
  </PnPTestSummary>
  <PnPTestSummary>
    <PnPConfigurationToTest>OnlineCred</PnPConfigurationToTest>
    <TestDate>Monday, February 15, 2016</TestDate>
    <TestTime>10:44 PM</TestTime>
    <PnPBranch>dev</PnPBranch>
    <VSBuildConfiguration>debug</VSBuildConfiguration>
    <NumberOfTests>294</NumberOfTests>
    <ElapsedTime>0h 56m 6s</ElapsedTime>
    <FailedTests>1</FailedTests>
    <SkippedTests>7</SkippedTests>
    <PassedTests>286</PassedTests>
    <MDResultFile>c:\pnpbuildtemp\PnPUnitTestResults-20160215-OnlineCred-635911766989384795.md</MDResultFile>
  </PnPTestSummary>
  <PnPTestSummary>
    <PnPConfigurationToTest>OnPremAppOnly</PnPConfigurationToTest>
    <TestDate>Monday, February 15, 2016</TestDate>
    <TestTime>10:23 PM</TestTime>
    <PnPBranch>dev</PnPBranch>
    <VSBuildConfiguration>debug15</VSBuildConfiguration>
    <NumberOfTests>286</NumberOfTests>
    <ElapsedTime>0h 20m 58s</ElapsedTime>
    <FailedTests>1</FailedTests>
    <SkippedTests>51</SkippedTests>
    <PassedTests>234</PassedTests>
    <MDResultFile>c:\pnpbuildtemp\PnPUnitTestResults-20160215-OnPremAppOnly-635911754217950240.md</MDResultFile>
  </PnPTestSummary>
  <PnPTestSummary>
    <PnPConfigurationToTest>OnPremCred</PnPConfigurationToTest>
    <TestDate>Monday, February 15, 2016</TestDate>
    <TestTime>10:00 PM</TestTime>
    <PnPBranch>dev</PnPBranch>
    <VSBuildConfiguration>debug15</VSBuildConfiguration>
    <NumberOfTests>286</NumberOfTests>
    <ElapsedTime>0h 23m 4s</ElapsedTime>
    <FailedTests>1</FailedTests>
    <SkippedTests>21</SkippedTests>
    <PassedTests>264</PassedTests>
    <MDResultFile>c:\pnpbuildtemp\PnPUnitTestResults-20160215-OnPremCred-635911740198152100.md</MDResultFile>
  </PnPTestSummary>
  <PnPTestSummary>
    <PnPConfigurationToTest>OnlineAppOnly</PnPConfigurationToTest>
    <TestDate>Monday, February 15, 2016</TestDate>
    <TestTime>11:31 PM</TestTime>
    <PnPBranch>dev</PnPBranch>
    <VSBuildConfiguration>debug</VSBuildConfiguration>
    <NumberOfTests>294</NumberOfTests>
    <ElapsedTime>0h 50m 18s</ElapsedTime>
    <FailedTests>2</FailedTests>
    <SkippedTests>39</SkippedTests>
    <PassedTests>253</PassedTests>
    <MDResultFile>c:\pnpbuildtemp\PnPUnitTestResults-20160215-OnlineAppOnly-635910930794839468.md</MDResultFile>
  </PnPTestSummary>
  <PnPTestSummary>
    <PnPConfigurationToTest>OnlineCred</PnPConfigurationToTest>
    <TestDate>Sunday, February 14, 2016</TestDate>
    <TestTime>10:45 PM</TestTime>
    <PnPBranch>dev</PnPBranch>
    <VSBuildConfiguration>debug</VSBuildConfiguration>
    <NumberOfTests>294</NumberOfTests>
    <ElapsedTime>0h 45m 57s</ElapsedTime>
    <FailedTests>4</FailedTests>
    <SkippedTests>7</SkippedTests>
    <PassedTests>283</PassedTests>
    <MDResultFile>c:\pnpbuildtemp\PnPUnitTestResults-20160214-OnlineCred-635910903039014093.md</MDResultFile>
  </PnPTestSummary>
  <PnPTestSummary>
    <PnPConfigurationToTest>OnPremAppOnly</PnPConfigurationToTest>
    <TestDate>Sunday, February 14, 2016</TestDate>
    <TestTime>10:23 PM</TestTime>
    <PnPBranch>dev</PnPBranch>
    <VSBuildConfiguration>debug15</VSBuildConfiguration>
    <NumberOfTests>286</NumberOfTests>
    <ElapsedTime>0h 21m 4s</ElapsedTime>
    <FailedTests>1</FailedTests>
    <SkippedTests>51</SkippedTests>
    <PassedTests>234</PassedTests>
    <MDResultFile>c:\pnpbuildtemp\PnPUnitTestResults-20160214-OnPremAppOnly-635910890193845875.md</MDResultFile>
  </PnPTestSummary>
  <PnPTestSummary>
    <PnPConfigurationToTest>OnPremCred</PnPConfigurationToTest>
    <TestDate>Sunday, February 14, 2016</TestDate>
    <TestTime>10:00 PM</TestTime>
    <PnPBranch>dev</PnPBranch>
    <VSBuildConfiguration>debug15</VSBuildConfiguration>
    <NumberOfTests>286</NumberOfTests>
    <ElapsedTime>0h 23m 1s</ElapsedTime>
    <FailedTests>1</FailedTests>
    <SkippedTests>21</SkippedTests>
    <PassedTests>264</PassedTests>
    <MDResultFile>c:\pnpbuildtemp\PnPUnitTestResults-20160214-OnPremCred-635910876199254582.md</MDResultFile>
  </PnPTestSummary>
  <PnPTestSummary>
    <PnPConfigurationToTest>OnlineAppOnly</PnPConfigurationToTest>
    <TestDate>Sunday, February 14, 2016</TestDate>
    <TestTime>11:43 PM</TestTime>
    <PnPBranch>dev</PnPBranch>
    <VSBuildConfiguration>debug</VSBuildConfiguration>
    <NumberOfTests>294</NumberOfTests>
    <ElapsedTime>1h 2m 33s</ElapsedTime>
    <FailedTests>3</FailedTests>
    <SkippedTests>39</SkippedTests>
    <PassedTests>252</PassedTests>
    <MDResultFile>c:\pnpbuildtemp\PnPUnitTestResults-20160214-OnlineAppOnly-635910074210874469.md</MDResultFile>
  </PnPTestSummary>
  <PnPTestSummary>
    <PnPConfigurationToTest>OnlineCred</PnPConfigurationToTest>
    <TestDate>Saturday, February 13, 2016</TestDate>
    <TestTime>10:49 PM</TestTime>
    <PnPBranch>dev</PnPBranch>
    <VSBuildConfiguration>debug</VSBuildConfiguration>
    <NumberOfTests>294</NumberOfTests>
    <ElapsedTime>0h 54m 11s</ElapsedTime>
    <FailedTests>1</FailedTests>
    <SkippedTests>7</SkippedTests>
    <PassedTests>286</PassedTests>
    <MDResultFile>c:\pnpbuildtemp\PnPUnitTestResults-20160213-OnlineCred-635910041493464976.md</MDResultFile>
  </PnPTestSummary>
  <PnPTestSummary>
    <PnPConfigurationToTest>OnPremAppOnly</PnPConfigurationToTest>
    <TestDate>Saturday, February 13, 2016</TestDate>
    <TestTime>10:23 PM</TestTime>
    <PnPBranch>dev</PnPBranch>
    <VSBuildConfiguration>debug15</VSBuildConfiguration>
    <NumberOfTests>286</NumberOfTests>
    <ElapsedTime>0h 25m 24s</ElapsedTime>
    <FailedTests>1</FailedTests>
    <SkippedTests>51</SkippedTests>
    <PassedTests>234</PassedTests>
    <MDResultFile>c:\pnpbuildtemp\PnPUnitTestResults-20160213-OnPremAppOnly-635910025994274901.md</MDResultFile>
  </PnPTestSummary>
  <PnPTestSummary>
    <PnPConfigurationToTest>OnPremCred</PnPConfigurationToTest>
    <TestDate>Saturday, February 13, 2016</TestDate>
    <TestTime>10:00 PM</TestTime>
    <PnPBranch>dev</PnPBranch>
    <VSBuildConfiguration>debug15</VSBuildConfiguration>
    <NumberOfTests>286</NumberOfTests>
    <ElapsedTime>0h 22m 42s</ElapsedTime>
    <FailedTests>1</FailedTests>
    <SkippedTests>21</SkippedTests>
    <PassedTests>264</PassedTests>
    <MDResultFile>c:\pnpbuildtemp\PnPUnitTestResults-20160213-OnPremCred-635910012188025443.md</MDResultFile>
  </PnPTestSummary>
  <PnPTestSummary>
    <PnPConfigurationToTest>OnlineAppOnly</PnPConfigurationToTest>
    <TestDate>Saturday, February 13, 2016</TestDate>
    <TestTime>11:39 PM</TestTime>
    <PnPBranch>dev</PnPBranch>
    <VSBuildConfiguration>debug</VSBuildConfiguration>
    <NumberOfTests>294</NumberOfTests>
    <ElapsedTime>0h 47m 15s</ElapsedTime>
    <FailedTests>2</FailedTests>
    <SkippedTests>39</SkippedTests>
    <PassedTests>253</PassedTests>
    <MDResultFile>c:\pnpbuildtemp\PnPUnitTestResults-20160213-OnlineAppOnly-635909207488051714.md</MDResultFile>
  </PnPTestSummary>
  <PnPTestSummary>
    <PnPConfigurationToTest>OnlineCred</PnPConfigurationToTest>
    <TestDate>Friday, February 12, 2016</TestDate>
    <TestTime>10:45 PM</TestTime>
    <PnPBranch>dev</PnPBranch>
    <VSBuildConfiguration>debug</VSBuildConfiguration>
    <NumberOfTests>294</NumberOfTests>
    <ElapsedTime>0h 53m 45s</ElapsedTime>
    <FailedTests>2</FailedTests>
    <SkippedTests>7</SkippedTests>
    <PassedTests>285</PassedTests>
    <MDResultFile>c:\pnpbuildtemp\PnPUnitTestResults-20160212-OnlineCred-635909175048714709.md</MDResultFile>
  </PnPTestSummary>
  <PnPTestSummary>
    <PnPConfigurationToTest>OnPremAppOnly</PnPConfigurationToTest>
    <TestDate>Friday, February 12, 2016</TestDate>
    <TestTime>10:23 PM</TestTime>
    <PnPBranch>dev</PnPBranch>
    <VSBuildConfiguration>debug15</VSBuildConfiguration>
    <NumberOfTests>286</NumberOfTests>
    <ElapsedTime>0h 21m 19s</ElapsedTime>
    <FailedTests>1</FailedTests>
    <SkippedTests>51</SkippedTests>
    <PassedTests>234</PassedTests>
    <MDResultFile>c:\pnpbuildtemp\PnPUnitTestResults-20160212-OnPremAppOnly-635909162073968840.md</MDResultFile>
  </PnPTestSummary>
  <PnPTestSummary>
    <PnPConfigurationToTest>OnPremCred</PnPConfigurationToTest>
    <TestDate>Friday, February 12, 2016</TestDate>
    <TestTime>10:00 PM</TestTime>
    <PnPBranch>dev</PnPBranch>
    <VSBuildConfiguration>debug15</VSBuildConfiguration>
    <NumberOfTests>286</NumberOfTests>
    <ElapsedTime>0h 22m 44s</ElapsedTime>
    <FailedTests>1</FailedTests>
    <SkippedTests>21</SkippedTests>
    <PassedTests>264</PassedTests>
    <MDResultFile>c:\pnpbuildtemp\PnPUnitTestResults-20160212-OnPremCred-635909148258071322.md</MDResultFile>
  </PnPTestSummary>
  <PnPTestSummary>
    <PnPConfigurationToTest>OnlineAppOnly</PnPConfigurationToTest>
    <TestDate>Friday, February 12, 2016</TestDate>
    <TestTime>11:41 PM</TestTime>
    <PnPBranch>dev</PnPBranch>
    <VSBuildConfiguration>debug</VSBuildConfiguration>
    <NumberOfTests>294</NumberOfTests>
    <ElapsedTime>0h 49m 15s</ElapsedTime>
    <FailedTests>1</FailedTests>
    <SkippedTests>39</SkippedTests>
    <PassedTests>254</PassedTests>
    <MDResultFile>c:\pnpbuildtemp\PnPUnitTestResults-20160212-OnlineAppOnly-635908345148483028.md</MDResultFile>
  </PnPTestSummary>
  <PnPTestSummary>
    <PnPConfigurationToTest>OnlineCred</PnPConfigurationToTest>
    <TestDate>Thursday, February 11, 2016</TestDate>
    <TestTime>10:45 PM</TestTime>
    <PnPBranch>dev</PnPBranch>
    <VSBuildConfiguration>debug</VSBuildConfiguration>
    <NumberOfTests>294</NumberOfTests>
    <ElapsedTime>0h 56m 31s</ElapsedTime>
    <FailedTests>1</FailedTests>
    <SkippedTests>7</SkippedTests>
    <PassedTests>286</PassedTests>
    <MDResultFile>c:\pnpbuildtemp\PnPUnitTestResults-20160211-OnlineCred-635908311051425224.md</MDResultFile>
  </PnPTestSummary>
  <PnPTestSummary>
    <PnPConfigurationToTest>OnPremAppOnly</PnPConfigurationToTest>
    <TestDate>Thursday, February 11, 2016</TestDate>
    <TestTime>10:23 PM</TestTime>
    <PnPBranch>dev</PnPBranch>
    <VSBuildConfiguration>debug15</VSBuildConfiguration>
    <NumberOfTests>286</NumberOfTests>
    <ElapsedTime>0h 20m 51s</ElapsedTime>
    <FailedTests>1</FailedTests>
    <SkippedTests>51</SkippedTests>
    <PassedTests>234</PassedTests>
    <MDResultFile>c:\pnpbuildtemp\PnPUnitTestResults-20160211-OnPremAppOnly-635908298345308701.md</MDResultFile>
  </PnPTestSummary>
  <PnPTestSummary>
    <PnPConfigurationToTest>OnPremCred</PnPConfigurationToTest>
    <TestDate>Thursday, February 11, 2016</TestDate>
    <TestTime>10:00 PM</TestTime>
    <PnPBranch>dev</PnPBranch>
    <VSBuildConfiguration>debug15</VSBuildConfiguration>
    <NumberOfTests>286</NumberOfTests>
    <ElapsedTime>0h 23m 9s</ElapsedTime>
    <FailedTests>1</FailedTests>
    <SkippedTests>21</SkippedTests>
    <PassedTests>264</PassedTests>
    <MDResultFile>c:\pnpbuildtemp\PnPUnitTestResults-20160211-OnPremCred-635908284263788797.md</MDResultFile>
  </PnPTestSummary>
  <PnPTestSummary>
    <PnPConfigurationToTest>OnlineAppOnly</PnPConfigurationToTest>
    <TestDate>Thursday, February 11, 2016</TestDate>
    <TestTime>11:37 PM</TestTime>
    <PnPBranch>dev</PnPBranch>
    <VSBuildConfiguration>debug</VSBuildConfiguration>
    <NumberOfTests>294</NumberOfTests>
    <ElapsedTime>1h 12m 31s</ElapsedTime>
    <FailedTests>1</FailedTests>
    <SkippedTests>39</SkippedTests>
    <PassedTests>254</PassedTests>
    <MDResultFile>c:\pnpbuildtemp\PnPUnitTestResults-20160211-OnlineAppOnly-635907478315376938.md</MDResultFile>
  </PnPTestSummary>
  <PnPTestSummary>
    <PnPConfigurationToTest>OnlineCred</PnPConfigurationToTest>
    <TestDate>Wednesday, February 10, 2016</TestDate>
    <TestTime>10:43 PM</TestTime>
    <PnPBranch>dev</PnPBranch>
    <VSBuildConfiguration>debug</VSBuildConfiguration>
    <NumberOfTests>294</NumberOfTests>
    <ElapsedTime>0h 52m 54s</ElapsedTime>
    <FailedTests>2</FailedTests>
    <SkippedTests>7</SkippedTests>
    <PassedTests>285</PassedTests>
    <MDResultFile>c:\pnpbuildtemp\PnPUnitTestResults-20160210-OnlineCred-635907446379665745.md</MDResultFile>
  </PnPTestSummary>
  <PnPTestSummary>
    <PnPConfigurationToTest>OnPremAppOnly</PnPConfigurationToTest>
    <TestDate>Wednesday, February 10, 2016</TestDate>
    <TestTime>10:23 PM</TestTime>
    <PnPBranch>dev</PnPBranch>
    <VSBuildConfiguration>debug15</VSBuildConfiguration>
    <NumberOfTests>286</NumberOfTests>
    <ElapsedTime>0h 20m 32s</ElapsedTime>
    <FailedTests>1</FailedTests>
    <SkippedTests>51</SkippedTests>
    <PassedTests>234</PassedTests>
    <MDResultFile>c:\pnpbuildtemp\PnPUnitTestResults-20160210-OnPremAppOnly-635907433869909875.md</MDResultFile>
  </PnPTestSummary>
  <PnPTestSummary>
    <PnPConfigurationToTest>OnPremCred</PnPConfigurationToTest>
    <TestDate>Wednesday, February 10, 2016</TestDate>
    <TestTime>10:00 PM</TestTime>
    <PnPBranch>dev</PnPBranch>
    <VSBuildConfiguration>debug15</VSBuildConfiguration>
    <NumberOfTests>286</NumberOfTests>
    <ElapsedTime>0h 22m 20s</ElapsedTime>
    <FailedTests>1</FailedTests>
    <SkippedTests>21</SkippedTests>
    <PassedTests>264</PassedTests>
    <MDResultFile>c:\pnpbuildtemp\PnPUnitTestResults-20160210-OnPremCred-635907420274270800.md</MDResultFile>
  </PnPTestSummary>
  <PnPTestSummary>
    <PnPConfigurationToTest>OnlineAppOnly</PnPConfigurationToTest>
    <TestDate>Wednesday, February 10, 2016</TestDate>
    <TestTime>11:43 PM</TestTime>
    <PnPBranch>dev</PnPBranch>
    <VSBuildConfiguration>debug</VSBuildConfiguration>
    <NumberOfTests>294</NumberOfTests>
    <ElapsedTime>1h 15m 21s</ElapsedTime>
    <FailedTests>3</FailedTests>
    <SkippedTests>39</SkippedTests>
    <PassedTests>252</PassedTests>
    <MDResultFile>c:\pnpbuildtemp\PnPUnitTestResults-20160210-OnlineAppOnly-635906618269978015.md</MDResultFile>
  </PnPTestSummary>
  <PnPTestSummary>
    <PnPConfigurationToTest>OnlineCred</PnPConfigurationToTest>
    <TestDate>Tuesday, February 9, 2016</TestDate>
    <TestTime>10:43 PM</TestTime>
    <PnPBranch>dev</PnPBranch>
    <VSBuildConfiguration>debug</VSBuildConfiguration>
    <NumberOfTests>294</NumberOfTests>
    <ElapsedTime>0h 59m 48s</ElapsedTime>
    <FailedTests>1</FailedTests>
    <SkippedTests>7</SkippedTests>
    <PassedTests>286</PassedTests>
    <MDResultFile>c:\pnpbuildtemp\PnPUnitTestResults-20160209-OnlineCred-635906582206264466.md</MDResultFile>
  </PnPTestSummary>
  <PnPTestSummary>
    <PnPConfigurationToTest>OnPremAppOnly</PnPConfigurationToTest>
    <TestDate>Tuesday, February 9, 2016</TestDate>
    <TestTime>10:22 PM</TestTime>
    <PnPBranch>dev</PnPBranch>
    <VSBuildConfiguration>debug15</VSBuildConfiguration>
    <NumberOfTests>286</NumberOfTests>
    <ElapsedTime>0h 20m 36s</ElapsedTime>
    <FailedTests>1</FailedTests>
    <SkippedTests>51</SkippedTests>
    <PassedTests>234</PassedTests>
    <MDResultFile>c:\pnpbuildtemp\PnPUnitTestResults-20160209-OnPremAppOnly-635906569653000670.md</MDResultFile>
  </PnPTestSummary>
  <PnPTestSummary>
    <PnPConfigurationToTest>OnPremCred</PnPConfigurationToTest>
    <TestDate>Tuesday, February 9, 2016</TestDate>
    <TestTime>10:00 PM</TestTime>
    <PnPBranch>dev</PnPBranch>
    <VSBuildConfiguration>debug15</VSBuildConfiguration>
    <NumberOfTests>286</NumberOfTests>
    <ElapsedTime>0h 22m 8s</ElapsedTime>
    <FailedTests>1</FailedTests>
    <SkippedTests>21</SkippedTests>
    <PassedTests>264</PassedTests>
    <MDResultFile>c:\pnpbuildtemp\PnPUnitTestResults-20160209-OnPremCred-635906556182936501.md</MDResultFile>
  </PnPTestSummary>
  <PnPTestSummary>
    <PnPConfigurationToTest>OnlineAppOnly</PnPConfigurationToTest>
    <TestDate>Tuesday, February 9, 2016</TestDate>
    <TestTime>11:32 PM</TestTime>
    <PnPBranch>dev</PnPBranch>
    <VSBuildConfiguration>debug</VSBuildConfiguration>
    <NumberOfTests>294</NumberOfTests>
    <ElapsedTime>1h 10m 11s</ElapsedTime>
    <FailedTests>1</FailedTests>
    <SkippedTests>39</SkippedTests>
    <PassedTests>254</PassedTests>
    <MDResultFile>c:\pnpbuildtemp\PnPUnitTestResults-20160209-OnlineAppOnly-635905747216160600.md</MDResultFile>
  </PnPTestSummary>
  <PnPTestSummary>
    <PnPConfigurationToTest>OnlineCred</PnPConfigurationToTest>
    <TestDate>Monday, February 8, 2016</TestDate>
    <TestTime>10:43 PM</TestTime>
    <PnPBranch>dev</PnPBranch>
    <VSBuildConfiguration>debug</VSBuildConfiguration>
    <NumberOfTests>294</NumberOfTests>
    <ElapsedTime>0h 48m 33s</ElapsedTime>
    <FailedTests>2</FailedTests>
    <SkippedTests>7</SkippedTests>
    <PassedTests>285</PassedTests>
    <MDResultFile>c:\pnpbuildtemp\PnPUnitTestResults-20160208-OnlineCred-635905717896208665.md</MDResultFile>
  </PnPTestSummary>
  <PnPTestSummary>
    <PnPConfigurationToTest>OnPremAppOnly</PnPConfigurationToTest>
    <TestDate>Monday, February 8, 2016</TestDate>
    <TestTime>10:22 PM</TestTime>
    <PnPBranch>dev</PnPBranch>
    <VSBuildConfiguration>debug15</VSBuildConfiguration>
    <NumberOfTests>286</NumberOfTests>
    <ElapsedTime>0h 20m 12s</ElapsedTime>
    <FailedTests>1</FailedTests>
    <SkippedTests>51</SkippedTests>
    <PassedTests>234</PassedTests>
    <MDResultFile>c:\pnpbuildtemp\PnPUnitTestResults-20160208-OnPremAppOnly-635905705579936158.md</MDResultFile>
  </PnPTestSummary>
  <PnPTestSummary>
    <PnPConfigurationToTest>OnPremCred</PnPConfigurationToTest>
    <TestDate>Monday, February 8, 2016</TestDate>
    <TestTime>10:00 PM</TestTime>
    <PnPBranch>dev</PnPBranch>
    <VSBuildConfiguration>debug15</VSBuildConfiguration>
    <NumberOfTests>286</NumberOfTests>
    <ElapsedTime>0h 21m 52s</ElapsedTime>
    <FailedTests>1</FailedTests>
    <SkippedTests>21</SkippedTests>
    <PassedTests>264</PassedTests>
    <MDResultFile>c:\pnpbuildtemp\PnPUnitTestResults-20160208-OnPremCred-635905692253651686.md</MDResultFile>
  </PnPTestSummary>
  <PnPTestSummary>
    <PnPConfigurationToTest>OnlineAppOnly</PnPConfigurationToTest>
    <TestDate>Monday, February 8, 2016</TestDate>
    <TestTime>11:42 PM</TestTime>
    <PnPBranch>dev</PnPBranch>
    <VSBuildConfiguration>debug</VSBuildConfiguration>
    <NumberOfTests>292</NumberOfTests>
    <ElapsedTime>0h 49m 8s</ElapsedTime>
    <FailedTests>3</FailedTests>
    <SkippedTests>37</SkippedTests>
    <PassedTests>252</PassedTests>
    <MDResultFile>c:\pnpbuildtemp\PnPUnitTestResults-20160208-OnlineAppOnly-635904889319526481.md</MDResultFile>
  </PnPTestSummary>
  <PnPTestSummary>
    <PnPConfigurationToTest>OnlineCred</PnPConfigurationToTest>
    <TestDate>Sunday, February 7, 2016</TestDate>
    <TestTime>10:41 PM</TestTime>
    <PnPBranch>dev</PnPBranch>
    <VSBuildConfiguration>debug</VSBuildConfiguration>
    <NumberOfTests>292</NumberOfTests>
    <ElapsedTime>1h 0m 16s</ElapsedTime>
    <FailedTests>2</FailedTests>
    <SkippedTests>5</SkippedTests>
    <PassedTests>285</PassedTests>
    <MDResultFile>c:\pnpbuildtemp\PnPUnitTestResults-20160207-OnlineCred-635904852984250664.md</MDResultFile>
  </PnPTestSummary>
  <PnPTestSummary>
    <PnPConfigurationToTest>OnPremAppOnly</PnPConfigurationToTest>
    <TestDate>Sunday, February 7, 2016</TestDate>
    <TestTime>10:21 PM</TestTime>
    <PnPBranch>dev</PnPBranch>
    <VSBuildConfiguration>debug15</VSBuildConfiguration>
    <NumberOfTests>284</NumberOfTests>
    <ElapsedTime>0h 19m 54s</ElapsedTime>
    <FailedTests>6</FailedTests>
    <SkippedTests>49</SkippedTests>
    <PassedTests>229</PassedTests>
    <MDResultFile>c:\pnpbuildtemp\PnPUnitTestResults-20160207-OnPremAppOnly-635904840860303073.md</MDResultFile>
  </PnPTestSummary>
  <PnPTestSummary>
    <PnPConfigurationToTest>OnPremCred</PnPConfigurationToTest>
    <TestDate>Sunday, February 7, 2016</TestDate>
    <TestTime>10:00 PM</TestTime>
    <PnPBranch>dev</PnPBranch>
    <VSBuildConfiguration>debug15</VSBuildConfiguration>
    <NumberOfTests>284</NumberOfTests>
    <ElapsedTime>0h 20m 48s</ElapsedTime>
    <FailedTests>6</FailedTests>
    <SkippedTests>19</SkippedTests>
    <PassedTests>259</PassedTests>
    <MDResultFile>c:\pnpbuildtemp\PnPUnitTestResults-20160207-OnPremCred-635904828199481984.md</MDResultFile>
  </PnPTestSummary>
  <PnPTestSummary>
    <PnPConfigurationToTest>OnlineAppOnly</PnPConfigurationToTest>
    <TestDate>Sunday, February 7, 2016</TestDate>
    <TestTime>5:43 PM</TestTime>
    <PnPBranch>dev</PnPBranch>
    <VSBuildConfiguration>debug</VSBuildConfiguration>
    <NumberOfTests>292</NumberOfTests>
    <ElapsedTime>0h 44m 57s</ElapsedTime>
    <FailedTests>6</FailedTests>
    <SkippedTests>37</SkippedTests>
    <PassedTests>249</PassedTests>
    <MDResultFile>c:\pnpbuildtemp\PnPUnitTestResults-20160207-OnlineAppOnly-635904674115743031.md</MDResultFile>
  </PnPTestSummary>
  <PnPTestSummary>
    <PnPConfigurationToTest>OnlineCred</PnPConfigurationToTest>
    <TestDate>Sunday, February 7, 2016</TestDate>
    <TestTime>4:54 PM</TestTime>
    <PnPBranch>dev</PnPBranch>
    <VSBuildConfiguration>debug</VSBuildConfiguration>
    <NumberOfTests>292</NumberOfTests>
    <ElapsedTime>0h 49m 1s</ElapsedTime>
    <FailedTests>9</FailedTests>
    <SkippedTests>5</SkippedTests>
    <PassedTests>278</PassedTests>
    <MDResultFile>c:\pnpbuildtemp\PnPUnitTestResults-20160207-OnlineCred-635904644543717339.md</MDResultFile>
  </PnPTestSummary>
  <PnPTestSummary>
    <PnPConfigurationToTest>OnPremAppOnly</PnPConfigurationToTest>
    <TestDate>Sunday, February 7, 2016</TestDate>
    <TestTime>4:34 PM</TestTime>
    <PnPBranch>dev</PnPBranch>
    <VSBuildConfiguration>debug15</VSBuildConfiguration>
    <NumberOfTests>284</NumberOfTests>
    <ElapsedTime>0h 19m 41s</ElapsedTime>
    <FailedTests>6</FailedTests>
    <SkippedTests>49</SkippedTests>
    <PassedTests>229</PassedTests>
    <MDResultFile>c:\pnpbuildtemp\PnPUnitTestResults-20160207-OnPremAppOnly-635904632572221016.md</MDResultFile>
  </PnPTestSummary>
  <PnPTestSummary>
    <PnPConfigurationToTest>OnPremCred</PnPConfigurationToTest>
    <TestDate>Sunday, February 7, 2016</TestDate>
    <TestTime>4:12 PM</TestTime>
    <PnPBranch>dev</PnPBranch>
    <VSBuildConfiguration>debug15</VSBuildConfiguration>
    <NumberOfTests>284</NumberOfTests>
    <ElapsedTime>0h 21m 58s</ElapsedTime>
    <FailedTests>6</FailedTests>
    <SkippedTests>19</SkippedTests>
    <PassedTests>259</PassedTests>
    <MDResultFile>c:\pnpbuildtemp\PnPUnitTestResults-20160207-OnPremCred-635904619236958675.md</MDResultFile>
  </PnPTestSummary>
</PnPUnitTestResults>